Workbook
Name Beg_Bal: '[1]Loan Amortization'!$C$19:$C$378
Name CompanyName: #REF!
Name CustomerLookup: #REF!
Name End_Bal: '[1]Loan Amortization'!$I$19:$I$378
Name Extra_Pay: '[1]Loan Amortization'!$E$19:$E$378
Name Int: '[1]Loan Amortization'!$H$19:$H$378
Name Interest_Rate: '[1]Loan Amortization'!$D$6
Name Invoice_No: #REF!
Name InvoiceNoDetails: "InvoiceDetails[Invoice No]"
Name Loan_Amount: '[1]Loan Amortization'!$D$5
Name Loan_Start: '[1]Loan Amortization'!$D$8
Name Loan_Years: '[1]Loan Amortization'!$D$7
Name Number_of_Payments: MATCH(0.01,End_Bal,-1)+1
Name Number_of_Payments: MATCH(0.01,End_Bal,-1)+1
Name Number_of_Payments: MATCH(0.01,End_Bal,-1)+1
Name Pay_Num: '[1]Loan Amortization'!$A$19:$A$378
Name Princ: '[1]Loan Amortization'!$G$19:$G$378
Name rngInvoice: #REF!
Name Sched_Pay: '[1]Loan Amortization'!$D$19:$D$378
Name Scheduled_Extra_Payments: '[1]Loan Amortization'!$D$9
Name Scheduled_Monthly_Payment: '[1]Loan Amortization'!$D$12
Name Total_Pay: '[1]Loan Amortization'!$F$19:$F$378
Name Values_Entered: IF(Loan_Amount*Interest_Rate*Loan_Years*Loan_Start>0,1,0)
Name Values_Entered: IF(Loan_Amount*Interest_Rate*Loan_Years*Loan_Start>0,1,0)
Name Values_Entered: IF(Loan_Amount*Interest_Rate*Loan_Years*Loan_Start>0,1,0)

Sheet KPIs
A4: Gross Rental Income: $ | B4: ='IS (Combined)'!D16 -> 830313.64
A5: Gross Other Income: $ | B5: ='IS (Combined)'!D31+'IS (Combined)'!D32+'IS (Combined)'!D33+'IS (Combined)'!D34+'IS (Combined)'!D35 -> 87785.74
A6: Operating Expenses: $ (includes property taxes, insurance, maintenance) | B6: ='IS (Combined)'!D81 -> 366889.71
A7: Net Operating Income (NOI): $ | B7: =B4+B5-B6 -> 551209.67
A8: Operating Cash Flow (After Debt Service): $ | B8: ='IS (Combined)'!D85 -> 263727.85
A9: Capital Expenditures: $ (unit renovations and common area upgrades) | B9: ='Fixed Assets'!E15+'Fixed Assets'!E16+'Fixed Assets'!E17+'Fixed Assets'!E18+'Fixed Assets'!E19+55382.62+10221.09+'Fixed Assets'!E20 -> 368524.38
A10: Debt Service Coverage Ratio: | B10: ='IS (Combined)'!D83/-'IS (Combined)'!D84 -> 1.9173723
A13: Property Financial Results | B13: Since Inception
A14: Total Revenues: $ | B14: ='IS (Combined)'!D36 -> 918099.38
A15: Net Operating Income (NOI): $ | B15: ='IS (Combined)'!D83 -> 551209.67
A16: Debt Service & Other: $ | B16: =-'IS (Combined)'!D84 -> 287481.82
A17: Capital Improvements: $ | B17: =B9 -> 368524.38
A18: Operating Cash Flow (After Debt Service): $ | B18: =B8 -> 263727.85
A19: Avg. Occupancy
A21: Inception: April 8, 2025

Sheet Analyzer
B2: #VALUE! | I2: Underwriting Assumptions | N2: Underwriting Comments:
I3: Vacancy Loss % | L3: 0.05
I4: Bad Debt % | L4: 0.02
I5: Concessions % | L5: 0
I7: Rent Escalator | L7: 0.03
I8: Other Income Escalator | L8: 0.01
I9: Expense Escalator | L9: 0.03
C10: Actual Q2 | E10: Budget
B12: ='[2]Data Entry'!B1 -> Allaire on 41st | C12: Since Inception DATA | I12: ACQUISITION (YEAR 0) | L12: POST ACQUISITION
B13: Financial Projections | C13: Actual Q3 | E13: Budget | I13: Acquisition | J13: 45755 | K13: 45838
C14: T3 | E14: T3 | I14: Analysis
B15: Cash Flow Projection: | D15: % | E15: quarters 2 | F15: % | G15: variance | I15: Year 0 | J15: Per Unit | K15: % | L15: Year 1 | M15: Per Unit | N15: % | O15: Year 2 | P15: Per Unit | Q15: % | R15: Year 3 | S15: Per Unit | T15: % | U15: Year 4 | V15: Per Unit | W15: % | X15: Year 5 | Y15: Per Unit | Z15: % | AA15: Year 6 | AB15: % | AC15: Year 7 | AD15: % | AE15: Year 8 | AF15: % | AG15: Year 9 | AH15: % | AI15: Year 10 | AJ15: % | AK15: Comments
B16: Average Rent | I16: =I21/'[2]Data Entry'!$C$11/12 -> 1954.4146 | M16: =L21/'[2]Data Entry'!$C$11/12 -> 2135.1119 | P16: =O21/'[2]Data Entry'!$C$11/12 -> 2316.8707 | S16: =R21/'[2]Data Entry'!$C$11/12 -> 2504.0822 | V16: =U21/'[2]Data Entry'!$C$11/12 -> 2579.2046 | Y16: =X21/'[2]Data Entry'!$C$11/12 -> 2656.5808 | AA16: =AA19/'[2]Data Entry'!$C$11/12 -> 2654.0939 | AC16: =AC19/'[2]Data Entry'!$C$11/12 -> 2707.1758 | AE16: =AE19/'[2]Data Entry'!$C$11/12 -> 2761.3193 | AG16: =AG19/'[2]Data Entry'!$C$11/12 -> 2816.5457 | AI16: =AI19/'[2]Data Entry'!$C$11/12 -> 2872.8766
B17: Average Annual Rent Increase | I17: 0 | M17: =(M16-I16)/I16 -> 0.09245596 | P17: =(P16-M16)/M16 -> 0.085128437 | S17: =(S16-P16)/P16 -> 0.080803606 | V17: =(V16-S16)/S16 -> 0.03 | Y17: =(Y16-V16)/V16 -> 0.03 | AA17: =(AA16-Y16)/Y16 -> -0.00093611671 | AC17: =(AC16-AA16)/AA16 -> 0.02 | AE17: =(AE16-AC16)/AC16 -> 0.02 | AG17: =(AG16-AE16)/AE16 -> 0.02 | AI17: =(AI16-AG16)/AG16 -> 0.02
B18: INCOME:
B19: Gross Rent | C19: ='IS (Combined)'!D12+'IS (Combined)'!D13 -> 899671.81 | D19: =+C19/$C$85 -> 0.97992857 | E19: =(I19/4)*2 -> 1002330 | F19: =+E19/$E$85 -> 1.0585217 | G19: =C19-E19 -> -102658.19 | I19: ='[2]Rent Analysis'!I23 -> 2004660 | J19: =+I19/'[2]Data Entry'!$C$11 -> 24447.073 | K19: =+I19/$I$85 -> 1.0585217 | L19: ='[2]Rent Analysis'!M23 -> 2274900 | M19: =+L19/'[2]Data Entry'!$C$11 -> 27742.683 | N19: =+L19/$L$85 -> 1.0772745 | O19: =+L19*(1+$L$7) -> 2343147 | P19: =+O19/'[2]Data Entry'!$C$11 -> 28574.963 | Q19: =+O19/$O$85 -> 1.0056618 | R19: =+O19*(1+$L$7) -> 2413441.4 | S19: =+R19/'[2]Data Entry'!$C$11 -> 29432.212 | T19: =+R19/$R$85 -> 0.96407555 | U19: =+R19*(1+$L$7) -> 2485844.7 | V19: =+U19/'[2]Data Entry'!$C$11 -> 30315.179 | W19: =+U19/$U$85 -> 0.96566226 | X19: =+U19*(1+$L$7) -> 2560420 | Y19: =+X19/'[2]Data Entry'!$C$11 -> 31224.634 | Z19: =+X19/$X$85 -> 0.96722323 | AA19: =X19*1.02 -> 2611628.4 | AB19: =AA19/$X$85 -> 0.9865677 | AC19: =AA19*1.02 -> 2663861 | AD19: =AC19/$X$85 -> 1.0062991 | AE19: =AC19*1.02 -> 2717138.2 | AF19: =AE19/$X$85 -> 1.026425 | AG19: =AE19*1.02 -> 2771480.9 | AH19: =AG19/$X$85 -> 1.0469535 | AI19: =AG19*1.02 -> 2826910.6 | AJ19: =AI19/$X$85 -> 1.0678926
B20: (Loss) / Gain to Old Lease | C20: 0 | D20: =+C20/$C$85 -> 0 | E20: =I20/2 -> -40758 | F20: =+E20/$E$85 -> -0.043042936 | G20: =C20-E20 -> 40758 | I20: ='[2]Rent Analysis'!G23-I19 -> -81516 | J20: =+I20/'[2]Data Entry'!$C$11 -> -994.09756 | K20: =+I20/$I$85 -> -0.043042936 | L20: =-L19+'[2]Rent Analysis'!M36 -> -173949.88 | M20: =+L20/'[2]Data Entry'!$C$11 -> -2121.3399 | N20: =+L20/$L$85 -> -0.082373631 | O20: =-O19+'[2]Rent Analysis'!M37 -> -63346.274 | P20: =+O20/'[2]Data Entry'!$C$11 -> -772.51553 | Q20: =+O20/$O$85 -> -0.027187763 | R20: =-R19+'[2]Rent Analysis'!M38 -> 50575.436 | S20: =+R20/'[2]Data Entry'!$C$11 -> 616.7736 | T20: =+R20/$R$85 -> 0.020202911 | U20: =-U19+'[2]Rent Analysis'!M39 -> 52092.699 | V20: =+U20/'[2]Data Entry'!$C$11 -> 635.27681 | W20: =+U20/$U$85 -> 0.020236161 | X20: =-X19+'[2]Rent Analysis'!M40 -> 53655.48 | Y20: =+X20/'[2]Data Entry'!$C$11 -> 654.33512 | Z20: =+X20/$X$85 -> 0.020268873 | AA20: =-AA19*0.01 -> -26116.284 | AB20: =AA20/$X$85 -> -0.009865677 | AC20: =-AC19*0.01 -> -26638.61 | AD20: =AC20/$X$85 -> -0.010062991 | AE20: =-AE19*0.01 -> -27171.382 | AF20: =AE20/$X$85 -> -0.01026425 | AG20: =-AG19*0.01 -> -27714.809 | AH20: =AG20/$X$85 -> -0.010469535 | AI20: =-AI19*0.01 -> -28269.106 | AJ20: =AI20/$X$85 -> -0.010678926
B21: Gross Possible Rent | C21: =SUM(C19:C20) -> 899671.81 | D21: =+C21/$C$85 -> 0.97992857 | E21: =SUM(E19:E20) -> 961572 | F21: =+E21/$E$85 -> 1.0154787 | G21: =SUM(G19:G20) -> -61900.19 | I21: =SUM(I19:I20) -> 1923144 | J21: =+I21/'[2]Data Entry'!$C$11 -> 23452.976 | K21: =+I21/$I$85 -> 1.0154787 | L21: =SUM(L19:L20) -> 2100950.1 | M21: =+L21/'[2]Data Entry'!$C$11 -> 25621.343 | N21: =+L21/$L$85 -> 0.99490091 | O21: =SUM(O19:O20) -> 2279800.7 | P21: =+O21/'[2]Data Entry'!$C$11 -> 27802.448 | Q21: =+O21/$O$85 -> 0.97847401 | R21: =SUM(R19:R20) -> 2464016.8 | S21: 26539 | T21: =+R21/$R$85 -> 0.98427846 | U21: =SUM(U19:U20) -> 2537937.4 | V21: 26539 | W21: =+U21/$U$85 -> 0.98589842 | X21: =SUM(X19:X20) -> 2614075.5 | Y21: 26539 | Z21: =+X21/$X$85 -> 0.98749211
B22: Deductions
B23: Bad Debt | C23: ='IS (Combined)'!D14 -> -54228.32 | D23: =+C23/$C$85 -> -0.05906585 | E23: =I23/2 -> -19231.44 | F23: =+E23/$E$85 -> -0.020309575 | G23: =C23-E23 -> -34996.88 | I23: =-$L$4*I21 -> -38462.88 | J23: =+I23/'[2]Data Entry'!$C$11 -> -469.05951 | K23: =+I23/$I$85 -> -0.020309575 | L23: =-$L$4*L21 -> -42019.002 | M23: =+L23/'[2]Data Entry'!$C$11 -> -512.42686 | N23: =+L23/$L$85 -> -0.019898018 | O23: =-$L$4*O21 -> -45596.015 | P23: =+O23/'[2]Data Entry'!$C$11 -> -556.04896 | Q23: =+O23/$O$85 -> -0.01956948 | R23: =-$L$4*R21 -> -49280.337 | S23: =+R23/'[2]Data Entry'!$C$11 -> -600.97972 | T23: =+R23/$R$85 -> -0.019685569 | U23: =-$L$4*U21 -> -50758.747 | V23: =+U23/'[2]Data Entry'!$C$11 -> -619.00911 | W23: =+U23/$U$85 -> -0.019717968 | X23: =-$L$4*X21 -> -52281.509 | Y23: =+X23/'[2]Data Entry'!$C$11 -> -637.57938 | Z23: =+X23/$X$85 -> -0.019749842
B24: Vacancy Loss | C24: 0 | D24: =+C24/$C$85 -> 0 | E24: =I24/2 -> -48078.6 | F24: =+E24/$E$85 -> -0.050773936 | G24: =C24-E24 -> 48078.6 | I24: =-$L$3*I21 -> -96157.2 | J24: =+I24/'[2]Data Entry'!$C$11 -> -1172.6488 | K24: =+I24/$I$85 -> -0.050773936 | L24: =-$L$3*L21 -> -105047.51 | M24: =+L24/'[2]Data Entry'!$C$11 -> -1281.0671 | N24: =+L24/$L$85 -> -0.049745046 | O24: =-$L$3*O21 -> -113990.04 | P24: =+O24/'[2]Data Entry'!$C$11 -> -1390.1224 | Q24: =+O24/$O$85 -> -0.0489237 | R24: =-$L$3*R21 -> -123200.84 | S24: =+R24/'[2]Data Entry'!$C$11 -> -1502.4493 | T24: =+R24/$R$85 -> -0.049213923 | U24: =-$L$3*U21 -> -126896.87 | V24: =+U24/'[2]Data Entry'!$C$11 -> -1547.5228 | W24: =+U24/$U$85 -> -0.049294921 | X24: =-$L$3*X21 -> -130703.77 | Y24: =+X24/'[2]Data Entry'!$C$11 -> -1593.9485 | Z24: =+X24/$X$85 -> -0.049374605
B25: Vacancy Loss - Model Units | C25: 0 | D25: =+C25/$C$85 -> 0 | E25: =I25/2 -> 0 | F25: =+E25/$E$85 -> 0 | G25: =C25-E25 -> 0 | I25: 0 | J25: =+I25/'[2]Data Entry'!$C$11 -> 0 | K25: =+I25/$I$85 -> 0 | L25: =+I25 -> 0 | M25: =+L25/'[2]Data Entry'!$C$11 -> 0 | N25: =+L25/$L$85 -> 0 | O25: =+L25*(1+$L$7) -> 0 | P25: =+O25/'[2]Data Entry'!$C$11 -> 0 | Q25: =+O25/$O$85 -> 0 | R25: =+O25*(1+$L$7) -> 0 | S25: =+R25/'[2]Data Entry'!$C$11 -> 0 | T25: =+R25/$R$85 -> 0 | U25: =+R25*(1+$L$7) -> 0 | V25: =+U25/'[2]Data Entry'!$C$11 -> 0 | W25: =+U25/$U$85 -> 0 | X25: =+U25*(1+$L$7) -> 0 | Y25: =+X25/'[2]Data Entry'!$C$11 -> 0 | Z25: =+X25/$X$85 -> 0
B26: Rent Concessions - Recurring | C26: 0 | D26: =+C26/$C$85 -> 0 | E26: =I26/2 -> 0 | F26: =+E26/$E$85 -> 0 | G26: =C26-E26 -> 0 | I26: =-$L$5*I21 -> 0 | J26: =+I26/'[2]Data Entry'!$C$11 -> 0 | K26: =+I26/$I$85 -> 0 | L26: =-$L$5*L21 -> 0 | M26: =+L26/'[2]Data Entry'!$C$11 -> 0 | N26: =+L26/$L$85 -> 0 | O26: =-$L$5*O21 -> 0 | P26: =+O26/'[2]Data Entry'!$C$11 -> 0 | Q26: =+O26/$O$85 -> 0 | R26: =-$L$5*R21 -> 0 | S26: =+R26/'[2]Data Entry'!$C$11 -> 0 | T26: =+R26/$R$85 -> 0 | U26: =-$L$5*U21 -> 0 | V26: =+U26/'[2]Data Entry'!$C$11 -> 0 | W26: =+U26/$U$85 -> 0 | X26: =-$L$5*X21 -> 0 | Y26: =+X26/'[2]Data Entry'!$C$11 -> 0 | Z26: =+X26/$X$85 -> 0
B27: Rent Concessions - One Time | C27: ='IS (Combined)'!D15 -> -15129.85 | D27: =+C27/$C$85 -> -0.016479534 | E27: =I27/2 -> 0 | F27: =+E27/$E$85 -> 0 | G27: =C27-E27 -> -15129.85 | I27: 0 | J27: =+I27/'[2]Data Entry'!$C$11 -> 0 | K27: =+I27/$I$85 -> 0 | L27: 0 | M27: =+L27/'[2]Data Entry'!$C$11 -> 0 | N27: =+L27/$L$85 -> 0 | O27: 0 | P27: =+O27/'[2]Data Entry'!$C$11 -> 0 | Q27: =+O27/$O$85 -> 0 | R27: 0 | S27: =+R27/'[2]Data Entry'!$C$11 -> 0 | T27: =+R27/$R$85 -> 0 | U27: =+R27 -> 0 | V27: =+U27/'[2]Data Entry'!$C$11 -> 0 | W27: =+U27/$U$85 -> 0 | X27: =+U27 -> 0 | Y27: =+X27/'[2]Data Entry'!$C$11 -> 0 | Z27: =+X27/$X$85 -> 0
B28: Employee Apartment Discounts | C28: 0 | D28: =+C28/$C$85 -> 0 | E28: =I28/2 -> 0 | F28: =+E28/$E$85 -> 0 | G28: =C28-E28 -> 0 | I28: 0 | J28: =+I28/'[2]Data Entry'!$C$11 -> 0 | K28: =+I28/$I$85 -> 0 | L28: =+I28 -> 0 | M28: =+L28/'[2]Data Entry'!$C$11 -> 0 | N28: =+L28/$L$85 -> 0 | O28: =+L28 -> 0 | P28: =+O28/'[2]Data Entry'!$C$11 -> 0 | Q28: =+O28/$O$85 -> 0 | R28: 0 | S28: =+R28/'[2]Data Entry'!$C$11 -> 0 | T28: =+R28/$R$85 -> 0 | U28: 0 | V28: =+U28/'[2]Data Entry'!$C$11 -> 0 | W28: =+U28/$U$85 -> 0 | X28: 0 | Y28: =+X28/'[2]Data Entry'!$C$11 -> 0 | Z28: =+X28/$X$85 -> 0
B29: Other | C29: 0 | D29: =+C29/$C$85 -> 0 | E29: =I29/2 -> 0 | F29: =+E29/$E$85 -> 0 | G29: =C29-E29 -> 0 | I29: 0 | J29: =+I29/'[2]Data Entry'!$C$11 -> 0 | K29: =+I29/$I$85 -> 0 | L29: 0 | M29: =+L29/'[2]Data Entry'!$C$11 -> 0 | N29: =+L29/$L$85 -> 0 | O29: 0 | P29: =+O29/'[2]Data Entry'!$C$11 -> 0 | Q29: =+O29/$O$85 -> 0 | R29: 0 | S29: =+R29/'[2]Data Entry'!$C$11 -> 0 | T29: =+R29/$R$85 -> 0 | U29: 0 | V29: =+U29/'[2]Data Entry'!$C$11 -> 0 | X29: 0 | Y29: =+X29/'[2]Data Entry'!$C$11 -> 0 | Z29: =+X29/$X$85 -> 0
B30: Other | C30: 0 | D30: =+C30/$C$85 -> 0 | E30: =I30/2 -> 0 | F30: =+E30/$E$85 -> 0 | G30: =C30-E30 -> 0 | I30: 0 | J30: =+I30/'[2]Data Entry'!$C$11 -> 0 | K30: =+I30/$I$85 -> 0 | L30: 0 | M30: =+L30/'[2]Data Entry'!$C$11 -> 0 | N30: =+L30/$L$85 -> 0 | O30: 0 | P30: =+O30/'[2]Data Entry'!$C$11 -> 0 | Q30: =+O30/$O$85 -> 0 | R30: 0 | S30: =+R30/'[2]Data Entry'!$C$11 -> 0 | T30: =+R30/$R$85 -> 0 | U30: 0 | V30: =+U30/'[2]Data Entry'!$C$11 -> 0 | X30: 0 | Y30: =+X30/'[2]Data Entry'!$C$11 -> 0 | Z30: =+X30/$X$85 -> 0
B31: Other | C31: 0 | D31: =+C31/$C$85 -> 0 | E31: =I31/2 -> 0 | F31: =+E31/$E$85 -> 0 | G31: =C31-E31 -> 0 | I31: 0 | J31: =+I31/'[2]Data Entry'!$C$11 -> 0 | K31: =+I31/$I$85 -> 0 | L31: 0 | M31: =+L31/'[2]Data Entry'!$C$11 -> 0 | N31: =+L31/$L$85 -> 0 | O31: 0 | P31: =+O31/'[2]Data Entry'!$C$11 -> 0 | Q31: =+O31/$O$85 -> 0 | R31: 0 | S31: =+R31/'[2]Data Entry'!$C$11 -> 0 | T31: =+R31/$R$85 -> 0 | U31: 0 | V31: =+U31/'[2]Data Entry'!$C$11 -> 0 | X31: 0 | Y31: =+X31/'[2]Data Entry'!$C$11 -> 0 | Z31: =+X31/$X$85 -> 0
B32: Other | C32: 0 | D32: =+C32/$C$85 -> 0 | E32: =I32/2 -> 0 | F32: =+E32/$E$85 -> 0 | G32: =C32-E32 -> 0 | I32: 0 | J32: =+I32/'[2]Data Entry'!$C$11 -> 0 | K32: =+I32/$I$85 -> 0 | L32: 0 | M32: =+L32/'[2]Data Entry'!$C$11 -> 0 | N32: =+L32/$L$85 -> 0 | O32: 0 | P32: =+O32/'[2]Data Entry'!$C$11 -> 0 | Q32: =+O32/$O$85 -> 0 | R32: 0 | S32: =+R32/'[2]Data Entry'!$C$11 -> 0 | T32: =+R32/$R$85 -> 0 | U32: 0 | V32: =+U32/'[2]Data Entry'!$C$11 -> 0 | W32: =+U32/$U$85 -> 0 | X32: 0 | Y32: =+X32/'[2]Data Entry'!$C$11 -> 0 | Z32: =+X32/$X$85 -> 0
B33: Total Deductions | C33: =SUM(C22:C32) -> -69358.17 | D33: =+C33/$C$85 -> -0.075545384 | E33: =SUM(E22:E32) -> -67310.04 | F33: =+E33/$E$85 -> -0.071083511 | G33: =SUM(G22:G32) -> -2048.13 | I33: =SUM(I22:I32) -> -134620.08 | J33: =+I33/'[2]Data Entry'!$C$11 -> -1641.7083 | K33: =+I33/$I$85 -> -0.071083511 | L33: =SUM(L22:L32) -> -147066.51 | M33: =+L33/'[2]Data Entry'!$C$11 -> -1793.494 | N33: =+L33/$L$85 -> -0.069643064 | O33: =SUM(O22:O32) -> -159586.05 | P33: =+O33/'[2]Data Entry'!$C$11 -> -1946.1714 | Q33: =+O33/$O$85 -> -0.06849318 | R33: =SUM(R22:R32) -> -172481.18 | S33: =+R33/'[2]Data Entry'!$C$11 -> -2103.429 | T33: =+R33/$R$85 -> -0.068899492 | U33: =SUM(U22:U32) -> -177655.61 | V33: =+U33/'[2]Data Entry'!$C$11 -> -2166.5319 | W33: =+U33/$U$85 -> -0.069012889 | X33: =SUM(X22:X32) -> -182985.28 | Y33: =+X33/'[2]Data Entry'!$C$11 -> -2231.5278 | Z33: =+X33/$X$85 -> -0.069124447
B34: Net Rental Income | C34: =+C21+C33 -> 830313.64 | D34: =+C34/$C$85 -> 0.90438318 | E34: =+E21+E33 -> 894261.96 | F34: =+E34/$E$85 -> 0.94439522 | G34: =+G21+G33 -> -63948.32 | I34: =+I21+I33 -> 1788523.9 | J34: =+I34/'[2]Data Entry'!$C$11 -> 21811.267 | K34: =+I34/$I$85 -> 0.94439522 | L34: =+L21+L33 -> 1953883.6 | M34: =+L34/'[2]Data Entry'!$C$11 -> 23827.849 | N34: =+L34/$L$85 -> 0.92525785 | O34: =+O21+O33 -> 2120214.7 | P34: =+O34/'[2]Data Entry'!$C$11 -> 25856.277 | Q34: =+O34/$O$85 -> 0.90998083 | R34: =+R21+R33 -> 2291535.7 | S34: =+R34/'[2]Data Entry'!$C$11 -> 27945.557 | T34: =+R34/$R$85 -> 0.91537897 | U34: =+U21+U33 -> 2360281.7 | V34: =+U34/'[2]Data Entry'!$C$11 -> 28783.924 | W34: =+U34/$U$85 -> 0.91688553 | X34: =+X21+X33 -> 2431090.2 | Y34: =+X34/'[2]Data Entry'!$C$11 -> 29647.441 | Z34: =+X34/$X$85 -> 0.91836766
B36: Other Income
B37: Administrative Fees | C37: 0 | D37: =+C37/$C$85 -> 0 | E37: =I37/2 -> 0 | F37: =+E37/$E$85 -> 0 | G37: =C37-E37 -> 0 | I37: 0 | J37: =+I37/'[2]Data Entry'!$C$11 -> 0 | K37: =+I37/$I$85 -> 0 | L37: =+I37*(1+$L$8) -> 0 | M37: =+L37/'[2]Data Entry'!$C$11 -> 0 | N37: =+L37/$L$85 -> 0 | O37: =+L37*(1+$L$8) -> 0 | P37: =+O37/'[2]Data Entry'!$C$11 -> 0 | Q37: =+O37/$O$85 -> 0 | R37: =+O37*(1+$L$8) -> 0 | S37: =+R37/'[2]Data Entry'!$C$11 -> 0 | T37: =+R37/$R$85 -> 0 | U37: =+R37*(1+$L$8) -> 0 | V37: =+U37/'[2]Data Entry'!$C$11 -> 0 | W37: =+U37/$U$85 -> 0 | X37: =+U37*(1+$L$8) -> 0 | Y37: =+X37/'[2]Data Entry'!$C$11 -> 0 | Z37: =+X37/$X$85 -> 0
B38: Alarm Charges | C38: 0 | D38: =+C38/$C$85 -> 0 | E38: =I38/2 -> 0 | F38: =+E38/$E$85 -> 0 | G38: =C38-E38 -> 0 | I38: 0 | J38: =+I38/'[2]Data Entry'!$C$11 -> 0 | K38: =+I38/$I$85 -> 0 | L38: =+I38*(1+$L$8) -> 0 | M38: =+L38/'[2]Data Entry'!$C$11 -> 0 | N38: =+L38/$L$85 -> 0 | O38: =+L38*(1+$L$8) -> 0 | P38: =+O38/'[2]Data Entry'!$C$11 -> 0 | Q38: =+O38/$O$85 -> 0 | R38: =+O38*(1+$L$8) -> 0 | S38: =+R38/'[2]Data Entry'!$C$11 -> 0 | T38: =+R38/$R$85 -> 0 | U38: =+R38*(1+$L$8) -> 0 | V38: =+U38/'[2]Data Entry'!$C$11 -> 0 | W38: =+U38/$U$85 -> 0 | X38: =+U38*(1+$L$8) -> 0 | Y38: =+X38/'[2]Data Entry'!$C$11 -> 0 | Z38: =+X38/$X$85 -> 0
B39: Appliance Rental Income | C39: 0 | D39: =+C39/$C$85 -> 0 | E39: =I39/2 -> 0 | F39: =+E39/$E$85 -> 0 | G39: =C39-E39 -> 0 | I39: 0 | J39: =+I39/'[2]Data Entry'!$C$11 -> 0 | K39: =+I39/$I$85 -> 0 | L39: =+I39*(1+$L$8) -> 0 | M39: =+L39/'[2]Data Entry'!$C$11 -> 0 | N39: =+L39/$L$85 -> 0 | O39: =+L39*(1+$L$8) -> 0 | P39: =+O39/'[2]Data Entry'!$C$11 -> 0 | Q39: =+O39/$O$85 -> 0 | R39: =+O39*(1+$L$8) -> 0 | S39: =+R39/'[2]Data Entry'!$C$11 -> 0 | T39: =+R39/$R$85 -> 0 | U39: =+R39*(1+$L$8) -> 0 | V39: =+U39/'[2]Data Entry'!$C$11 -> 0 | W39: =+U39/$U$85 -> 0 | X39: =+U39*(1+$L$8) -> 0 | Y39: =+X39/'[2]Data Entry'!$C$11 -> 0 | Z39: =+X39/$X$85 -> 0
B40: Application Fees | C40: ='IS (Combined)'!D22 -> 1350 | D40: =+C40/$C$85 -> 0.0014704291 | E40: =I40/2 -> 0 | F40: =+E40/$E$85 -> 0 | G40: =C40-E40 -> 1350 | I40: 0 | J40: =+I40/'[2]Data Entry'!$C$11 -> 0 | K40: =+I40/$I$85 -> 0 | L40: =+I40*(1+$L$8) -> 0 | M40: =+L40/'[2]Data Entry'!$C$11 -> 0 | N40: =+L40/$L$85 -> 0 | O40: =+L40*(1+$L$8) -> 0 | P40: =+O40/'[2]Data Entry'!$C$11 -> 0 | Q40: =+O40/$O$85 -> 0 | R40: =+O40*(1+$L$8) -> 0 | S40: =+R40/'[2]Data Entry'!$C$11 -> 0 | T40: =+R40/$R$85 -> 0 | U40: =+R40*(1+$L$8) -> 0 | V40: =+U40/'[2]Data Entry'!$C$11 -> 0 | W40: =+U40/$U$85 -> 0 | X40: =+U40*(1+$L$8) -> 0 | Y40: =+X40/'[2]Data Entry'!$C$11 -> 0 | Z40: =+X40/$X$85 -> 0
B41: Attorney / Court Fees | C41: ='IS (Combined)'!D19 -> 2780.92 | D41: =+C41/$C$85 -> 0.0030289967 | E41: =I41/2 -> 233 | F41: =+E41/$E$85 -> 0.00024606222 | G41: =C41-E41 -> 2547.92 | I41: 466 | J41: =+I41/'[2]Data Entry'!$C$11 -> 5.6829268 | K41: =+I41/$I$85 -> 0.00024606222 | L41: =+I41*(1+$L$8) -> 470.66 | M41: =+L41/'[2]Data Entry'!$C$11 -> 5.7397561 | N41: =+L41/$L$85 -> 0.00022288014 | O41: =+L41*(1+$L$8) -> 475.3666 | P41: =+O41/'[2]Data Entry'!$C$11 -> 5.7971537 | Q41: =+O41/$O$85 -> 0.00020402391 | R41: =+O41*(1+$L$8) -> 480.12027 | S41: =+R41/'[2]Data Entry'!$C$11 -> 5.8551252 | T41: =+R41/$R$85 -> 0.00019178929 | U41: =+R41*(1+$L$8) -> 484.92147 | V41: =+U41/'[2]Data Entry'!$C$11 -> 5.9136764 | W41: =+U41/$U$85 -> 0.00018837475 | X41: =+U41*(1+$L$8) -> 489.77068 | Y41: =+X41/'[2]Data Entry'!$C$11 -> 5.9728132 | Z41: =+X41/$X$85 -> 0.00018501558
B42: Bad Debt Recovery | C42: 0 | D42: =+C42/$C$85 -> 0 | E42: =I42/2 -> 0 | F42: =+E42/$E$85 -> 0 | G42: =C42-E42 -> 0 | I42: 0 | J42: =+I42/'[2]Data Entry'!$C$11 -> 0 | K42: =+I42/$I$85 -> 0 | L42: =+I42*(1+$L$8) -> 0 | M42: =+L42/'[2]Data Entry'!$C$11 -> 0 | N42: =+L42/$L$85 -> 0 | O42: =+L42*(1+$L$8) -> 0 | P42: =+O42/'[2]Data Entry'!$C$11 -> 0 | Q42: =+O42/$O$85 -> 0 | R42: =+O42*(1+$L$8) -> 0 | S42: =+R42/'[2]Data Entry'!$C$11 -> 0 | T42: =+R42/$R$85 -> 0 | U42: =+R42*(1+$L$8) -> 0 | V42: =+U42/'[2]Data Entry'!$C$11 -> 0 | W42: =+U42/$U$85 -> 0 | X42: =+U42*(1+$L$8) -> 0 | Y42: =+X42/'[2]Data Entry'!$C$11 -> 0 | Z42: =+X42/$X$85 -> 0
B43: Cable Fees (Access & Marketing) | C43: 0 | D43: =+C43/$C$85 -> 0 | E43: =I43/2 -> 0 | F43: =+E43/$E$85 -> 0 | G43: =C43-E43 -> 0 | I43: 0 | J43: =+I43/'[2]Data Entry'!$C$11 -> 0 | K43: =+I43/$I$85 -> 0 | L43: =+I43*(1+$L$8) -> 0 | M43: =+L43/'[2]Data Entry'!$C$11 -> 0 | N43: =+L43/$L$85 -> 0 | O43: =+L43*(1+$L$8) -> 0 | P43: =+O43/'[2]Data Entry'!$C$11 -> 0 | Q43: =+O43/$O$85 -> 0 | R43: =+O43*(1+$L$8) -> 0 | S43: =+R43/'[2]Data Entry'!$C$11 -> 0 | T43: =+R43/$R$85 -> 0 | U43: =+R43*(1+$L$8) -> 0 | V43: =+U43/'[2]Data Entry'!$C$11 -> 0 | W43: =+U43/$U$85 -> 0 | X43: =+U43*(1+$L$8) -> 0 | Y43: =+X43/'[2]Data Entry'!$C$11 -> 0 | Z43: =+X43/$X$85 -> 0
B44: Clubhouse or Facility Rental | C44: 0 | D44: =+C44/$C$85 -> 0 | E44: =I44/2 -> 0 | F44: =+E44/$E$85 -> 0 | G44: =C44-E44 -> 0 | I44: 0 | J44: =+I44/'[2]Data Entry'!$C$11 -> 0 | K44: =+I44/$I$85 -> 0 | L44: =+I44*(1+$L$8) -> 0 | M44: =+L44/'[2]Data Entry'!$C$11 -> 0 | N44: =+L44/$L$85 -> 0 | O44: =+L44*(1+$L$8) -> 0 | P44: =+O44/'[2]Data Entry'!$C$11 -> 0 | Q44: =+O44/$O$85 -> 0 | R44: =+O44*(1+$L$8) -> 0 | S44: =+R44/'[2]Data Entry'!$C$11 -> 0 | T44: =+R44/$R$85 -> 0 | U44: =+R44*(1+$L$8) -> 0 | V44: =+U44/'[2]Data Entry'!$C$11 -> 0 | W44: =+U44/$U$85 -> 0 | X44: =+U44*(1+$L$8) -> 0 | Y44: =+X44/'[2]Data Entry'!$C$11 -> 0 | Z44: =+X44/$X$85 -> 0
B45: Concession Repayment | C45: 0 | D45: =+C45/$C$85 -> 0 | E45: =I45/2 -> 0 | F45: =+E45/$E$85 -> 0 | G45: =C45-E45 -> 0 | I45: 0 | J45: =+I45/'[2]Data Entry'!$C$11 -> 0 | K45: =+I45/$I$85 -> 0 | L45: =+I45*(1+$L$8) -> 0 | M45: =+L45/'[2]Data Entry'!$C$11 -> 0 | N45: =+L45/$L$85 -> 0 | O45: =+L45*(1+$L$8) -> 0 | P45: =+O45/'[2]Data Entry'!$C$11 -> 0 | Q45: =+O45/$O$85 -> 0 | R45: =+O45*(1+$L$8) -> 0 | S45: =+R45/'[2]Data Entry'!$C$11 -> 0 | T45: =+R45/$R$85 -> 0 | U45: =+R45*(1+$L$8) -> 0 | V45: =+U45/'[2]Data Entry'!$C$11 -> 0 | W45: =+U45/$U$85 -> 0 | X45: =+U45*(1+$L$8) -> 0 | Y45: =+X45/'[2]Data Entry'!$C$11 -> 0 | Z45: =+X45/$X$85 -> 0
B46: Credit Card Processing Fees | C46: 0 | D46: =+C46/$C$85 -> 0 | E46: =I46/2 -> 0 | F46: =+E46/$E$85 -> 0 | G46: =C46-E46 -> 0 | I46: 0 | J46: =+I46/'[2]Data Entry'!$C$11 -> 0 | K46: =+I46/$I$85 -> 0 | L46: =+I46*(1+$L$8) -> 0 | M46: =+L46/'[2]Data Entry'!$C$11 -> 0 | N46: =+L46/$L$85 -> 0 | O46: =+L46*(1+$L$8) -> 0 | P46: =+O46/'[2]Data Entry'!$C$11 -> 0 | Q46: =+O46/$O$85 -> 0 | R46: =+O46*(1+$L$8) -> 0 | S46: =+R46/'[2]Data Entry'!$C$11 -> 0 | T46: =+R46/$R$85 -> 0 | U46: =+R46*(1+$L$8) -> 0 | V46: =+U46/'[2]Data Entry'!$C$11 -> 0 | W46: =+U46/$U$85 -> 0 | X46: =+U46*(1+$L$8) -> 0 | Y46: =+X46/'[2]Data Entry'!$C$11 -> 0 | Z46: =+X46/$X$85 -> 0
B47: Deposits & Hold Fees Forfeited | C47: ='IS (Combined)'!D32 -> 16760 | D47: =+C47/$C$85 -> 0.018255104 | E47: =I47/2 -> 540 | F47: =+E47/$E$85 -> 0.00057027296 | G47: =C47-E47 -> 16220 | I47: 1080 | J47: =+I47/'[2]Data Entry'!$C$11 -> 13.170732 | K47: =+I47/$I$85 -> 0.00057027296 | L47: =+I47*(1+$L$8) -> 1090.8 | M47: =+L47/'[2]Data Entry'!$C$11 -> 13.302439 | N47: =+L47/$L$85 -> 0.00051654625 | O47: =+L47*(1+$L$8) -> 1101.708 | P47: =+O47/'[2]Data Entry'!$C$11 -> 13.435463 | Q47: =+O47/$O$85 -> 0.00047284512 | R47: =+O47*(1+$L$8) -> 1112.7251 | S47: =+R47/'[2]Data Entry'!$C$11 -> 13.569818 | T47: =+R47/$R$85 -> 0.0004444902 | U47: =+R47*(1+$L$8) -> 1123.8523 | V47: =+U47/'[2]Data Entry'!$C$11 -> 13.705516 | W47: =+U47/$U$85 -> 0.00043657667 | X47: =+U47*(1+$L$8) -> 1135.0909 | Y47: =+X47/'[2]Data Entry'!$C$11 -> 13.842571 | Z47: =+X47/$X$85 -> 0.00042879147
B48: Garage & Parking Rental Income | C48: 0 | D48: =+C48/$C$85 -> 0 | E48: =I48/2 -> 0 | F48: =+E48/$E$85 -> 0 | G48: =C48-E48 -> 0 | I48: 0 | J48: =+I48/'[2]Data Entry'!$C$11 -> 0 | K48: =+I48/$I$85 -> 0 | L48: =+I48*(1+$L$8) -> 0 | M48: =+L48/'[2]Data Entry'!$C$11 -> 0 | N48: =+L48/$L$85 -> 0 | O48: =+L48*(1+$L$8) -> 0 | P48: =+O48/'[2]Data Entry'!$C$11 -> 0 | Q48: =+O48/$O$85 -> 0 | R48: =+O48*(1+$L$8) -> 0 | S48: =+R48/'[2]Data Entry'!$C$11 -> 0 | T48: =+R48/$R$85 -> 0 | U48: =+R48*(1+$L$8) -> 0 | V48: =+U48/'[2]Data Entry'!$C$11 -> 0 | W48: =+U48/$U$85 -> 0 | X48: =+U48*(1+$L$8) -> 0 | Y48: =+X48/'[2]Data Entry'!$C$11 -> 0 | Z48: =+X48/$X$85 -> 0
B49: Holding Deposit | C49: ='IS (Combined)'!D26 -> 5300 | D49: =+C49/$C$85 -> 0.0057727955 | E49: =I49/2 -> 1650 | F49: =+E49/$E$85 -> 0.0017425007 | G49: =C49-E49 -> 3650 | I49: 3300 | J49: =+I49/'[2]Data Entry'!$C$11 -> 40.243902 | K49: =+I49/$I$85 -> 0.0017425007 | L49: =+I49*(1+$L$8) -> 3333 | M49: =+L49/'[2]Data Entry'!$C$11 -> 40.646341 | N49: =+L49/$L$85 -> 0.0015783358 | O49: =+L49*(1+$L$8) -> 3366.33 | P49: =+O49/'[2]Data Entry'!$C$11 -> 41.052805 | Q49: =+O49/$O$85 -> 0.0014448045 | R49: =+O49*(1+$L$8) -> 3399.9933 | S49: =+R49/'[2]Data Entry'!$C$11 -> 41.463333 | T49: =+R49/$R$85 -> 0.0013581645 | U49: =+R49*(1+$L$8) -> 3433.9932 | V49: =+U49/'[2]Data Entry'!$C$11 -> 41.877966 | W49: =+U49/$U$85 -> 0.0013339843 | X49: =+U49*(1+$L$8) -> 3468.3332 | Y49: =+X49/'[2]Data Entry'!$C$11 -> 42.296746 | Z49: =+X49/$X$85 -> 0.0013101962 | AA49: =X49 -> 3468.3332 | AB49: =AA49/$X$85 -> 0.0013101962 | AC49: =AA49 -> 3468.3332 | AD49: =AC49/$X$85 -> 0.0013101962 | AE49: =AC49 -> 3468.3332 | AF49: =AE49/$X$85 -> 0.0013101962 | AG49: =AE49 -> 3468.3332 | AH49: =AG49/$X$85 -> 0.0013101962 | AI49: =AG49 -> 3468.3332 | AJ49: =AI49/$X$85 -> 0.0013101962
B50: Insurance Income | C50: ='IS (Combined)'!D24+'IS (Combined)'!D25 -> 5344.24 | D50: =+C50/$C$85 -> 0.005820982 | E50: =I50/2 -> 10398.5 | F50: =+E50/$E$85 -> 0.010981451 | G50: =C50-E50 -> -5054.26 | I50: 20797 | J50: =+I50/'[2]Data Entry'!$C$11 -> 253.62195 | K50: =+I50/$I$85 -> 0.010981451 | L50: =+I50*(1+$L$8) -> 21004.97 | M50: =+L50/'[2]Data Entry'!$C$11 -> 256.15817 | N50: =+L50/$L$85 -> 0.0099468634 | O50: =+L50*(1+$L$8) -> 21215.02 | P50: =+O50/'[2]Data Entry'!$C$11 -> 258.71975 | Q50: =+O50/$O$85 -> 0.0091053332 | R50: =+O50*(1+$L$8) -> 21427.17 | S50: =+R50/'[2]Data Entry'!$C$11 -> 261.30695 | T50: =+R50/$R$85 -> 0.0085593172 | U50: =+R50*(1+$L$8) -> 21641.442 | V50: =+U50/'[2]Data Entry'!$C$11 -> 263.92002 | W50: =+U50/$U$85 -> 0.0084069306 | X50: =+U50*(1+$L$8) -> 21857.856 | Y50: =+X50/'[2]Data Entry'!$C$11 -> 266.55922 | Z50: =+X50/$X$85 -> 0.008257015 | AA50: =X50 -> 21857.856 | AB50: =AA50/$X$85 -> 0.008257015 | AC50: =AA50 -> 21857.856 | AD50: =AC50/$X$85 -> 0.008257015 | AE50: =AC50 -> 21857.856 | AF50: =AE50/$X$85 -> 0.008257015 | AG50: =AE50 -> 21857.856 | AH50: =AG50/$X$85 -> 0.008257015 | AI50: =AG50 -> 21857.856 | AJ50: =AI50/$X$85 -> 0.008257015
B51: Interest Income | C51: 0 | D51: =+C51/$C$85 -> 0 | E51: =I51/2 -> 52 | F51: =+E51/$E$85 -> 5.4915174e-05 | G51: =C51-E51 -> -52 | I51: 104 | J51: =+I51/'[2]Data Entry'!$C$11 -> 1.2682927 | K51: =+I51/$I$85 -> 5.4915174e-05 | L51: =+I51*(1+$L$8) -> 105.04 | M51: =+L51/'[2]Data Entry'!$C$11 -> 1.2809756 | N51: =+L51/$L$85 -> 4.9741491e-05 | O51: =+L51*(1+$L$8) -> 106.0904 | P51: =+O51/'[2]Data Entry'!$C$11 -> 1.2937854 | Q51: =+O51/$O$85 -> 4.5533233e-05 | R51: =+O51*(1+$L$8) -> 107.1513 | S51: =+R51/'[2]Data Entry'!$C$11 -> 1.3067232 | T51: =+R51/$R$85 -> 4.280276e-05 | U51: =+R51*(1+$L$8) -> 108.22282 | V51: =+U51/'[2]Data Entry'!$C$11 -> 1.3197905 | W51: =+U51/$U$85 -> 4.2040716e-05 | X51: =+U51*(1+$L$8) -> 109.30505 | Y51: =+X51/'[2]Data Entry'!$C$11 -> 1.3329884 | Z51: =+X51/$X$85 -> 4.129103e-05
B52: Late Charge Fees | C52: ='IS (Combined)'!D28 -> 9473.42 | D52: =+C52/$C$85 -> 0.010318513 | E52: =I52/2 -> 15511 | F52: =+E52/$E$85 -> 0.016380563 | G52: =C52-E52 -> -6037.58 | I52: 31022 | J52: =+I52/'[2]Data Entry'!$C$11 -> 378.31707 | K52: =+I52/$I$85 -> 0.016380563 | L52: =+I52*(1+$L$8) -> 31332.22 | M52: =+L52/'[2]Data Entry'!$C$11 -> 382.10024 | N52: =+L52/$L$85 -> 0.014837313 | O52: =+L52*(1+$L$8) -> 31645.542 | P52: =+O52/'[2]Data Entry'!$C$11 -> 385.92125 | Q52: =+O52/$O$85 -> 0.013582038 | R52: =+O52*(1+$L$8) -> 31961.998 | S52: =+R52/'[2]Data Entry'!$C$11 -> 389.78046 | T52: =+R52/$R$85 -> 0.012767569 | U52: =+R52*(1+$L$8) -> 32281.618 | V52: =+U52/'[2]Data Entry'!$C$11 -> 393.67826 | W52: =+U52/$U$85 -> 0.012540261 | X52: =+U52*(1+$L$8) -> 32604.434 | Y52: =+X52/'[2]Data Entry'!$C$11 -> 397.61505 | Z52: =+X52/$X$85 -> 0.012316638 | AA52: =-AA19*0.01 -> -26116.284 | AB52: =AA52/$X$85 -> -0.009865677 | AC52: =-AC19*0.01 -> -26638.61 | AD52: =AC52/$X$85 -> -0.010062991 | AE52: =-AE19*0.01 -> -27171.382 | AF52: =AE52/$X$85 -> -0.01026425 | AG52: =-AG19*0.01 -> -27714.809 | AH52: =AG52/$X$85 -> -0.010469535 | AI52: =-AI19*0.01 -> -28269.106 | AJ52: =AI52/$X$85 -> -0.010678926
B53: Laundry Income | C53: ='IS (Combined)'!D33 -> 849.56 | D53: =+C53/$C$85 -> 0.00092534645 | E53: =I53/2 -> 2954.5 | F53: =+E53/$E$85 -> 0.0031201324 | G53: =C53-E53 -> -2104.94 | I53: 5909 | J53: =+I53/'[2]Data Entry'!$C$11 -> 72.060976 | K53: =+I53/$I$85 -> 0.0031201324 | L53: =+I53*(1+$L$8) -> 5968.09 | M53: =+L53/'[2]Data Entry'!$C$11 -> 72.781585 | N53: =+L53/$L$85 -> 0.0028261776 | O53: =+L53*(1+$L$8) -> 6027.7709 | P53: =+O53/'[2]Data Entry'!$C$11 -> 73.509401 | Q53: =+O53/$O$85 -> 0.0025870757 | R53: =+O53*(1+$L$8) -> 6088.0486 | S53: =+R53/'[2]Data Entry'!$C$11 -> 74.244495 | T53: =+R53/$R$85 -> 0.0024319376 | U53: =+R53*(1+$L$8) -> 6148.9291 | V53: =+U53/'[2]Data Entry'!$C$11 -> 74.98694 | W53: =+U53/$U$85 -> 0.0023886403 | X53: =+U53*(1+$L$8) -> 6210.4184 | Y53: =+X53/'[2]Data Entry'!$C$11 -> 75.73681 | Z53: =+X53/$X$85 -> 0.0023460452 | AA53: =X53 -> 6210.4184 | AB53: =AA53/$X$85 -> 0.0023460452 | AC53: =AA53 -> 6210.4184 | AD53: =AC53/$X$85 -> 0.0023460452 | AE53: =AC53 -> 6210.4184 | AF53: =AE53/$X$85 -> 0.0023460452 | AG53: =AE53 -> 6210.4184 | AH53: =AG53/$X$85 -> 0.0023460452 | AI53: =AG53 -> 6210.4184 | AJ53: =AI53/$X$85 -> 0.0023460452
B54: Lease Termination/Breakage Fees | C54: ='IS (Combined)'!D27 -> 17996.8 | D54: =+C54/$C$85 -> 0.019602235 | E54: =I54/2 -> 1237.5 | F54: =+E54/$E$85 -> 0.0013068755 | G54: =C54-E54 -> 16759.3 | I54: 2475 | J54: =+I54/'[2]Data Entry'!$C$11 -> 30.182927 | K54: =+I54/$I$85 -> 0.0013068755 | L54: =+I54*(1+$L$8) -> 2499.75 | M54: =+L54/'[2]Data Entry'!$C$11 -> 30.484756 | N54: =+L54/$L$85 -> 0.0011837518 | O54: =+L54*(1+$L$8) -> 2524.7475 | P54: =+O54/'[2]Data Entry'!$C$11 -> 30.789604 | Q54: =+O54/$O$85 -> 0.0010836034 | R54: =+O54*(1+$L$8) -> 2549.995 | S54: =+R54/'[2]Data Entry'!$C$11 -> 31.0975 | T54: =+R54/$R$85 -> 0.0010186234 | U54: =+R54*(1+$L$8) -> 2575.4949 | V54: =+U54/'[2]Data Entry'!$C$11 -> 31.408475 | W54: =+U54/$U$85 -> 0.0010004882 | X54: =+U54*(1+$L$8) -> 2601.2499 | Y54: =+X54/'[2]Data Entry'!$C$11 -> 31.722559 | Z54: =+X54/$X$85 -> 0.00098264711 | AA54: =X54 -> 2601.2499 | AB54: =AA54/$X$85 -> 0.00098264711 | AC54: =AA54 -> 2601.2499 | AD54: =AC54/$X$85 -> 0.00098264711 | AE54: =AC54 -> 2601.2499 | AF54: =AE54/$X$85 -> 0.00098264711 | AG54: =AE54 -> 2601.2499 | AH54: =AG54/$X$85 -> 0.00098264711 | AI54: =AG54 -> 2601.2499 | AJ54: =AI54/$X$85 -> 0.00098264711
B55: Miscellaneous Income | C55: ='IS (Combined)'!D35 -> 1103.25 | D55: =+C55/$C$85 -> 0.0012016673 | E55: =I55/2 -> -862 | F55: =+E55/$E$85 -> -0.00091032462 | G55: =C55-E55 -> 1965.25 | I55: -1724 | J55: =+I55/'[2]Data Entry'!$C$11 -> -21.02439 | K55: =+I55/$I$85 -> -0.00091032462 | L55: =+I55*(1+$L$8) -> -1741.24 | M55: =+L55/'[2]Data Entry'!$C$11 -> -21.234634 | N55: =+L55/$L$85 -> -0.00082456087 | O55: =+L55*(1+$L$8) -> -1758.6524 | P55: =+O55/'[2]Data Entry'!$C$11 -> -21.44698 | Q55: =+O55/$O$85 -> -0.00075480091 | R55: =+O55*(1+$L$8) -> -1776.2389 | S55: =+R55/'[2]Data Entry'!$C$11 -> -21.66145 | T55: =+R55/$R$85 -> -0.00070953805 | U55: =+R55*(1+$L$8) -> -1794.0013 | V55: =+U55/'[2]Data Entry'!$C$11 -> -21.878065 | W55: =+U55/$U$85 -> -0.00069690572 | X55: =+U55*(1+$L$8) -> -1811.9413 | Y55: =+X55/'[2]Data Entry'!$C$11 -> -22.096845 | Z55: =+X55/$X$85 -> -0.00068447823 | AA55: =-AA19*0.06 -> -156697.7 | AB55: =AA55/$X$85 -> -0.059194062 | AC55: =-AC19*0.06 -> -159831.66 | AD55: =AC55/$X$85 -> -0.060377943 | AE55: =-AE19*0.06 -> -163028.29 | AF55: =AE55/$X$85 -> -0.061585502 | AG55: =-AG19*0.06 -> -166288.86 | AH55: =AG55/$X$85 -> -0.062817212 | AI55: =-AI19*0.06 -> -169614.63 | AJ55: =AI55/$X$85 -> -0.064073556
B56: Month to Month Fees | C56: 0 | D56: =+C56/$C$85 -> 0 | E56: =I56/2 -> 0 | F56: =+E56/$E$85 -> 0 | G56: =C56-E56 -> 0 | I56: 0 | J56: =+I56/'[2]Data Entry'!$C$11 -> 0 | K56: =+I56/$I$85 -> 0 | L56: =+I56*(1+$L$8) -> 0 | M56: =+L56/'[2]Data Entry'!$C$11 -> 0 | N56: =+L56/$L$85 -> 0 | O56: =+L56*(1+$L$8) -> 0 | P56: =+O56/'[2]Data Entry'!$C$11 -> 0 | Q56: =+O56/$O$85 -> 0 | R56: =+O56*(1+$L$8) -> 0 | S56: =+R56/'[2]Data Entry'!$C$11 -> 0 | T56: =+R56/$R$85 -> 0 | U56: =+R56*(1+$L$8) -> 0 | V56: =+U56/'[2]Data Entry'!$C$11 -> 0 | W56: =+U56/$U$85 -> 0 | X56: =+U56*(1+$L$8) -> 0 | Y56: =+X56/'[2]Data Entry'!$C$11 -> 0 | Z56: =+X56/$X$85 -> 0 | AA56: =SUM(AA19:AA55) -> 2436836 | AB56: =AA56/$X$85 -> 0.92053819 | AC56: =SUM(AC19:AC55) -> 2484889.9 | AD56: =AC56/$X$85 -> 0.93869103 | AE56: =SUM(AE19:AE55) -> 2533905 | AF56: =AE56/$X$85 -> 0.95720693 | AG56: =SUM(AG19:AG55) -> 2583900.3 | AH56: =AG56/$X$85 -> 0.97609316 | AI56: =SUM(AI19:AI55) -> 2634895.6 | AJ56: =AI56/$X$85 -> 0.9953571
B57: Pest Control Fees | C57: 0 | D57: =+C57/$C$85 -> 0 | E57: =I57/2 -> 0 | F57: =+E57/$E$85 -> 0 | G57: =C57-E57 -> 0 | I57: 0 | J57: =+I57/'[2]Data Entry'!$C$11 -> 0 | K57: =+I57/$I$85 -> 0 | L57: =+I57*(1+$L$8) -> 0 | M57: =+L57/'[2]Data Entry'!$C$11 -> 0 | N57: =+L57/$L$85 -> 0 | O57: =+L57*(1+$L$8) -> 0 | P57: =+O57/'[2]Data Entry'!$C$11 -> 0 | Q57: =+O57/$O$85 -> 0 | R57: =+O57*(1+$L$8) -> 0 | S57: =+R57/'[2]Data Entry'!$C$11 -> 0 | T57: =+R57/$R$85 -> 0 | U57: =+R57*(1+$L$8) -> 0 | V57: =+U57/'[2]Data Entry'!$C$11 -> 0 | W57: =+U57/$U$85 -> 0 | X57: =+U57*(1+$L$8) -> 0 | Y57: =+X57/'[2]Data Entry'!$C$11 -> 0 | Z57: =+X57/$X$85 -> 0 | AA57: =X57*1.01 -> 0 | AB57: =AA57/$X$85 -> 0 | AC57: =AA57*1.01 -> 0 | AD57: =AC57/$X$85 -> 0 | AE57: =AC57*1.01 -> 0 | AF57: =AE57/$X$85 -> 0 | AG57: =AE57*1.01 -> 0 | AH57: =AG57/$X$85 -> 0 | AI57: =AG57*1.01 -> 0 | AJ57: =AI57/$X$85 -> 0
B58: Pet Fees - Non-Refundable | C58: ='IS (Combined)'!D21 -> 236.25 | D58: =+C58/$C$85 -> 0.00025732508 | E58: =I58/2 -> 957.5 | F58: =+E58/$E$85 -> 0.0010111784 | G58: =C58-E58 -> -721.25 | I58: 1915 | J58: =+I58/'[2]Data Entry'!$C$11 -> 23.353659 | K58: =+I58/$I$85 -> 0.0010111784 | L58: =+I58*(1+$L$8) -> 1934.15 | M58: =+L58/'[2]Data Entry'!$C$11 -> 23.587195 | N58: =+L58/$L$85 -> 0.00091591303 | O58: =+L58*(1+$L$8) -> 1953.4915 | P58: =+O58/'[2]Data Entry'!$C$11 -> 23.823067 | Q58: =+O58/$O$85 -> 0.00083842444 | R58: =+O58*(1+$L$8) -> 1973.0264 | S58: =+R58/'[2]Data Entry'!$C$11 -> 24.061298 | T58: =+R58/$R$85 -> 0.00078814697 | U58: =+R58*(1+$L$8) -> 1992.7567 | V58: =+U58/'[2]Data Entry'!$C$11 -> 24.301911 | W58: =+U58/$U$85 -> 0.00077411511 | X58: =+U58*(1+$L$8) -> 2012.6842 | Y58: =+X58/'[2]Data Entry'!$C$11 -> 24.54493 | Z58: =+X58/$X$85 -> 0.0007603108 | AA58: =X58*1.01 -> 2032.8111 | AB58: =AA58/$X$85 -> 0.00076791391 | AC58: =AA58*1.01 -> 2053.1392 | AD58: =AC58/$X$85 -> 0.00077559304 | AE58: =AC58*1.01 -> 2073.6706 | AF58: =AE58/$X$85 -> 0.00078334898 | AG58: =AE58*1.01 -> 2094.4073 | AH58: =AG58/$X$85 -> 0.00079118246 | AI58: =AG58*1.01 -> 2115.3514 | AJ58: =AI58/$X$85 -> 0.00079909429
B59: Pet Rent | C59: ='IS (Combined)'!D20 -> 193.72 | D59: =+C59/$C$85 -> 0.00021100112 | E59: =I59/2 -> 1250 | F59: =+E59/$E$85 -> 0.0013200763 | G59: =C59-E59 -> -1056.28 | I59: 2500 | J59: =+I59/'[2]Data Entry'!$C$11 -> 30.487805 | K59: =+I59/$I$85 -> 0.0013200763 | L59: =+I59*(1+$L$8) -> 2525 | M59: =+L59/'[2]Data Entry'!$C$11 -> 30.792683 | N59: =+L59/$L$85 -> 0.0011957089 | O59: =+L59*(1+$L$8) -> 2550.25 | P59: =+O59/'[2]Data Entry'!$C$11 -> 31.10061 | Q59: =+O59/$O$85 -> 0.0010945489 | R59: =+O59*(1+$L$8) -> 2575.7525 | S59: =+R59/'[2]Data Entry'!$C$11 -> 31.411616 | T59: =+R59/$R$85 -> 0.0010289125 | U59: =+R59*(1+$L$8) -> 2601.51 | V59: =+U59/'[2]Data Entry'!$C$11 -> 31.725732 | W59: =+U59/$U$85 -> 0.0010105941 | X59: =+U59*(1+$L$8) -> 2627.5251 | Y59: =+X59/'[2]Data Entry'!$C$11 -> 32.042989 | Z59: =+X59/$X$85 -> 0.00099257284
B60: Resident Cleaning Charges | C60: 0 | D60: =+C60/$C$85 -> 0 | E60: =I60/2 -> 0 | F60: =+E60/$E$85 -> 0 | G60: =C60-E60 -> 0 | I60: 0 | J60: =+I60/'[2]Data Entry'!$C$11 -> 0 | K60: =+I60/$I$85 -> 0 | L60: =+I60*(1+$L$8) -> 0 | M60: =+L60/'[2]Data Entry'!$C$11 -> 0 | N60: =+L60/$L$85 -> 0 | O60: =+L60*(1+$L$8) -> 0 | P60: =+O60/'[2]Data Entry'!$C$11 -> 0 | Q60: =+O60/$O$85 -> 0 | R60: =+O60*(1+$L$8) -> 0 | S60: =+R60/'[2]Data Entry'!$C$11 -> 0 | T60: =+R60/$R$85 -> 0 | U60: =+R60*(1+$L$8) -> 0 | V60: =+U60/'[2]Data Entry'!$C$11 -> 0 | W60: =+U60/$U$85 -> 0 | X60: =+U60*(1+$L$8) -> 0 | Y60: =+X60/'[2]Data Entry'!$C$11 -> 0 | Z60: =+X60/$X$85 -> 0 | AA60: =X60 -> 0 | AB60: =AA60/$X$85 -> 0 | AC60: =AA60 -> 0 | AD60: =AC60/$X$85 -> 0 | AE60: =AC60 -> 0 | AF60: =AE60/$X$85 -> 0 | AG60: =AE60 -> 0 | AH60: =AG60/$X$85 -> 0 | AI60: =AG60 -> 0 | AJ60: =AI60/$X$85 -> 0
B61: Resident Misc. Income | C61: 0 | D61: =+C61/$C$85 -> 0 | E61: =I61/2 -> 0 | F61: =+E61/$E$85 -> 0 | G61: =C61-E61 -> 0 | I61: 0 | J61: =+I61/'[2]Data Entry'!$C$11 -> 0 | K61: =+I61/$I$85 -> 0 | L61: =+I61*(1+$L$8) -> 0 | M61: =+L61/'[2]Data Entry'!$C$11 -> 0 | N61: =+L61/$L$85 -> 0 | O61: =+L61*(1+$L$8) -> 0 | P61: =+O61/'[2]Data Entry'!$C$11 -> 0 | Q61: =+O61/$O$85 -> 0 | R61: =+O61*(1+$L$8) -> 0 | S61: =+R61/'[2]Data Entry'!$C$11 -> 0 | T61: =+R61/$R$85 -> 0 | U61: =+R61*(1+$L$8) -> 0 | V61: =+U61/'[2]Data Entry'!$C$11 -> 0 | W61: =+U61/$U$85 -> 0 | X61: =+U61*(1+$L$8) -> 0 | Y61: =+X61/'[2]Data Entry'!$C$11 -> 0 | Z61: =+X61/$X$85 -> 0 | AA61: =X61 -> 0 | AB61: =AA61/$X$85 -> 0 | AC61: =AA61 -> 0 | AD61: =AC61/$X$85 -> 0 | AE61: =AC61 -> 0 | AF61: =AE61/$X$85 -> 0 | AG61: =AE61 -> 0 | AH61: =AG61/$X$85 -> 0 | AI61: =AG61 -> 0 | AJ61: =AI61/$X$85 -> 0
B62: Short Term Lease Premium | C62: 0 | D62: =+C62/$C$85 -> 0 | E62: =I62/2 -> 2695.5 | F62: =+E62/$E$85 -> 0.0028466125 | G62: =C62-E62 -> -2695.5 | I62: 5391 | J62: =+I62/'[2]Data Entry'!$C$11 -> 65.743902 | K62: =+I62/$I$85 -> 0.0028466125 | L62: =+I62*(1+$L$8) -> 5444.91 | M62: =+L62/'[2]Data Entry'!$C$11 -> 66.401341 | N62: =+L62/$L$85 -> 0.0025784267 | O62: =+L62*(1+$L$8) -> 5499.3591 | P62: =+O62/'[2]Data Entry'!$C$11 -> 67.065355 | Q62: =+O62/$O$85 -> 0.0023602852 | R62: =+O62*(1+$L$8) -> 5554.3527 | S62: =+R62/'[2]Data Entry'!$C$11 -> 67.736008 | T62: =+R62/$R$85 -> 0.0022187469 | U62: =+R62*(1+$L$8) -> 5609.8962 | V62: =+U62/'[2]Data Entry'!$C$11 -> 68.413369 | W62: =+U62/$U$85 -> 0.0021792452 | X62: =+U62*(1+$L$8) -> 5665.9952 | Y62: =+X62/'[2]Data Entry'!$C$11 -> 69.097502 | Z62: =+X62/$X$85 -> 0.0021403841 | AA62: =X62 -> 5665.9952 | AB62: =AA62/$X$85 -> 0.0021403841 | AC62: =AA62 -> 5665.9952 | AD62: =AC62/$X$85 -> 0.0021403841 | AE62: =AC62 -> 5665.9952 | AF62: =AE62/$X$85 -> 0.0021403841 | AG62: =AE62 -> 5665.9952 | AH62: =AG62/$X$85 -> 0.0021403841 | AI62: =AG62 -> 5665.9952 | AJ62: =AI62/$X$85 -> 0.0021403841
B63: Storage Space Rental Income | C63: 0 | D63: =+C63/$C$85 -> 0 | E63: =I63/2 -> 0 | F63: =+E63/$E$85 -> 0 | G63: =C63-E63 -> 0 | I63: 0 | J63: =+I63/'[2]Data Entry'!$C$11 -> 0 | K63: =+I63/$I$85 -> 0 | L63: =+I63*(1+$L$8) -> 0 | M63: =+L63/'[2]Data Entry'!$C$11 -> 0 | N63: =+L63/$L$85 -> 0 | O63: =+L63*(1+$L$8) -> 0 | P63: =+O63/'[2]Data Entry'!$C$11 -> 0 | Q63: =+O63/$O$85 -> 0 | R63: =+O63*(1+$L$8) -> 0 | S63: =+R63/'[2]Data Entry'!$C$11 -> 0 | T63: =+R63/$R$85 -> 0 | U63: =+R63*(1+$L$8) -> 0 | V63: =+U63/'[2]Data Entry'!$C$11 -> 0 | W63: =+U63/$U$85 -> 0 | X63: =+U63*(1+$L$8) -> 0 | Y63: =+X63/'[2]Data Entry'!$C$11 -> 0 | Z63: =+X63/$X$85 -> 0 | AA63: =X63 -> 0 | AB63: =AA63/$X$85 -> 0 | AC63: =AA63 -> 0 | AD63: =AC63/$X$85 -> 0 | AE63: =AC63 -> 0 | AF63: =AE63/$X$85 -> 0 | AG63: =AE63 -> 0 | AH63: =AG63/$X$85 -> 0 | AI63: =AG63 -> 0 | AJ63: =AI63/$X$85 -> 0
B64: Utility Bill Back - Electric | C64: 0 | D64: =+C64/$C$85 -> 0 | E64: =I64/2 -> 61 | F64: =+E64/$E$85 -> 6.4419724e-05 | G64: =C64-E64 -> -61 | I64: 122 | J64: =+I64/'[2]Data Entry'!$C$11 -> 1.4878049 | K64: =+I64/$I$85 -> 6.4419724e-05 | L64: =+I64*(1+$L$8) -> 123.22 | M64: =+L64/'[2]Data Entry'!$C$11 -> 1.5026829 | N64: =+L64/$L$85 -> 5.8350595e-05 | O64: =+L64*(1+$L$8) -> 124.4522 | P64: =+O64/'[2]Data Entry'!$C$11 -> 1.5177098 | Q64: =+O64/$O$85 -> 5.3413985e-05 | R64: =+O64*(1+$L$8) -> 125.69672 | S64: =+R64/'[2]Data Entry'!$C$11 -> 1.5328869 | T64: =+R64/$R$85 -> 5.021093e-05 | U64: =+R64*(1+$L$8) -> 126.95369 | V64: =+U64/'[2]Data Entry'!$C$11 -> 1.5482157 | W64: =+U64/$U$85 -> 4.9316994e-05 | X64: =+U64*(1+$L$8) -> 128.22323 | Y64: =+X64/'[2]Data Entry'!$C$11 -> 1.5636979 | Z64: =+X64/$X$85 -> 4.8437555e-05 | AA64: =X64 -> 128.22323 | AB64: =AA64/$X$85 -> 4.8437555e-05 | AC64: =AA64 -> 128.22323 | AD64: =AC64/$X$85 -> 4.8437555e-05 | AE64: =AC64 -> 128.22323 | AF64: =AE64/$X$85 -> 4.8437555e-05 | AG64: =AE64 -> 128.22323 | AH64: =AG64/$X$85 -> 4.8437555e-05 | AI64: =AG64 -> 128.22323 | AJ64: =AI64/$X$85 -> 4.8437555e-05
B65: Utility Bill Back - General | C65: ='IS (Combined)'!D29 -> 24467.27 | D65: =+C65/$C$85 -> 0.026649915 | E65: =I65/2 -> 5786 | F65: =+E65/$E$85 -> 0.0061103692 | G65: =C65-E65 -> 18681.27 | I65: 11572 | J65: =+I65/'[2]Data Entry'!$C$11 -> 141.12195 | K65: =+I65/$I$85 -> 0.0061103692 | L65: 31688 | M65: =+L65/'[2]Data Entry'!$C$11 -> 386.43902 | N65: =+L65/$L$85 -> 0.015005792 | O65: 31688 | P65: =+O65/'[2]Data Entry'!$C$11 -> 386.43902 | Q65: =+O65/$O$85 -> 0.013600261 | R65: =+O65*(1+$L$8) -> 32004.88 | S65: =+R65/'[2]Data Entry'!$C$11 -> 390.30341 | T65: =+R65/$R$85 -> 0.012784699 | U65: =+R65*(1+$L$8) -> 32324.929 | V65: =+U65/'[2]Data Entry'!$C$11 -> 394.20645 | W65: =+U65/$U$85 -> 0.012557085 | X65: =+U65*(1+$L$8) -> 32648.178 | Y65: =+X65/'[2]Data Entry'!$C$11 -> 398.14851 | Z65: =+X65/$X$85 -> 0.012333163 | AA65: =X65 -> 32648.178 | AB65: =AA65/$X$85 -> 0.012333163 | AC65: =AA65 -> 32648.178 | AD65: =AC65/$X$85 -> 0.012333163 | AE65: =AC65 -> 32648.178 | AF65: =AE65/$X$85 -> 0.012333163 | AG65: =AE65 -> 32648.178 | AH65: =AG65/$X$85 -> 0.012333163 | AI65: =AG65 -> 32648.178 | AJ65: =AI65/$X$85 -> 0.012333163
B66: Utility Bill Back - Water | C66: 0 | D66: =+C66/$C$85 -> 0 | E66: =I66/2 -> 12000 | F66: =+E66/$E$85 -> 0.012672733 | G66: =C66-E66 -> -12000 | I66: 24000 | J66: =+I66/'[2]Data Entry'!$C$11 -> 292.68293 | K66: =+I66/$I$85 -> 0.012672733 | L66: 33150 | M66: =+L66/'[2]Data Entry'!$C$11 -> 404.26829 | N66: =+L66/$L$85 -> 0.015698119 | O66: 66300 | P66: =+O66/'[2]Data Entry'!$C$11 -> 808.53659 | Q66: =+O66/$O$85 -> 0.028455481 | R66: =+O66*(1+$L$8) -> 66963 | S66: =+R66/'[2]Data Entry'!$C$11 -> 816.62195 | T66: =+R66/$R$85 -> 0.026749102 | U66: =+R66*(1+$L$8) -> 67632.63 | V66: =+U66/'[2]Data Entry'!$C$11 -> 824.78817 | W66: =+U66/$U$85 -> 0.026272872 | X66: =+U66*(1+$L$8) -> 68308.956 | Y66: =+X66/'[2]Data Entry'!$C$11 -> 833.03605 | Z66: =+X66/$X$85 -> 0.025804364 | AA66: =X66 -> 68308.956 | AB66: =AA66/$X$85 -> 0.025804364 | AC66: =AA66 -> 68308.956 | AD66: =AC66/$X$85 -> 0.025804364 | AE66: =AC66 -> 68308.956 | AF66: =AE66/$X$85 -> 0.025804364 | AG66: =AE66 -> 68308.956 | AH66: =AG66/$X$85 -> 0.025804364 | AI66: =AG66 -> 68308.956 | AJ66: =AI66/$X$85 -> 0.025804364
B67: Utility Bill Back - Sewer | C67: 0 | D67: =+C67/$C$85 -> 0 | E67: =I67/2 -> 0 | F67: =+E67/$E$85 -> 0 | G67: =C67-E67 -> 0 | I67: 0 | J67: =+I67/'[2]Data Entry'!$C$11 -> 0 | K67: =+I67/$I$85 -> 0 | L67: =+I67*(1+$L$8) -> 0 | M67: =+L67/'[2]Data Entry'!$C$11 -> 0 | N67: =+L67/$L$85 -> 0 | O67: =+L67*(1+$L$8) -> 0 | P67: =+O67/'[2]Data Entry'!$C$11 -> 0 | Q67: =+O67/$O$85 -> 0 | R67: =+O67*(1+$L$8) -> 0 | S67: =+R67/'[2]Data Entry'!$C$11 -> 0 | T67: =+R67/$R$85 -> 0 | U67: =+R67*(1+$L$8) -> 0 | V67: =+U67/'[2]Data Entry'!$C$11 -> 0 | W67: =+U67/$U$85 -> 0 | X67: =+U67*(1+$L$8) -> 0 | Y67: =+X67/'[2]Data Entry'!$C$11 -> 0 | Z67: =+X67/$X$85 -> 0 | AA67: =X67 -> 0 | AB67: =AA67/$X$85 -> 0 | AC67: =AA67 -> 0 | AD67: =AC67/$X$85 -> 0 | AE67: =AC67 -> 0 | AF67: =AE67/$X$85 -> 0 | AG67: =AE67 -> 0 | AH67: =AG67/$X$85 -> 0 | AI67: =AG67 -> 0 | AJ67: =AI67/$X$85 -> 0
B68: Utility Bill Back - Trash | C68: 0 | D68: =+C68/$C$85 -> 0 | E68: =I68/2 -> 0 | F68: =+E68/$E$85 -> 0 | G68: =C68-E68 -> 0 | I68: 0 | J68: =+I68/'[2]Data Entry'!$C$11 -> 0 | K68: =+I68/$I$85 -> 0 | L68: =SUM(I97/2) -> 22565 | M68: =+L68/'[2]Data Entry'!$C$11 -> 275.18293 | N68: =+L68/$L$85 -> 0.010685613 | O68: =SUM(I97*0.9) -> 40617 | P68: =+O68/'[2]Data Entry'!$C$11 -> 495.32927 | Q68: =+O68/$O$85 -> 0.017432523 | R68: =+O68*(1+$L$8) -> 41023.17 | S68: =+R68/'[2]Data Entry'!$C$11 -> 500.28256 | T68: =+R68/$R$85 -> 0.016387154 | U68: =+R68*(1+$L$8) -> 41433.402 | V68: =+U68/'[2]Data Entry'!$C$11 -> 505.28539 | W68: =+U68/$U$85 -> 0.016095403 | X68: =+U68*(1+$L$8) -> 41847.736 | Y68: =+X68/'[2]Data Entry'!$C$11 -> 510.33824 | Z68: =+X68/$X$85 -> 0.015808384 | AA68: =X68 -> 41847.736 | AB68: =AA68/$X$85 -> 0.015808384 | AC68: =AA68 -> 41847.736 | AD68: =AC68/$X$85 -> 0.015808384 | AE68: =AC68 -> 41847.736 | AF68: =AE68/$X$85 -> 0.015808384 | AG68: =AE68 -> 41847.736 | AH68: =AG68/$X$85 -> 0.015808384 | AI68: =AG68 -> 41847.736 | AJ68: =AI68/$X$85 -> 0.015808384
B69: Utility Cost Recovery Surcharge (UCRS) | C69: 0 | D69: =+C69/$C$85 -> 0 | E69: =I69/2 -> 0 | F69: =+E69/$E$85 -> 0 | G69: =C69-E69 -> 0 | I69: 0 | J69: =+I69/'[2]Data Entry'!$C$11 -> 0 | K69: =+I69/$I$85 -> 0 | L69: =+I69*(1+$L$8) -> 0 | M69: =+L69/'[2]Data Entry'!$C$11 -> 0 | N69: =+L69/$L$85 -> 0 | O69: =+L69*(1+$L$8) -> 0 | P69: =+O69/'[2]Data Entry'!$C$11 -> 0 | Q69: =+O69/$O$85 -> 0 | R69: =+O69*(1+$L$8) -> 0 | S69: =+R69/'[2]Data Entry'!$C$11 -> 0 | T69: =+R69/$R$85 -> 0 | U69: =+R69*(1+$L$8) -> 0 | V69: =+U69/'[2]Data Entry'!$C$11 -> 0 | W69: =+U69/$U$85 -> 0 | X69: =+U69*(1+$L$8) -> 0 | Y69: =+X69/'[2]Data Entry'!$C$11 -> 0 | Z69: =+X69/$X$85 -> 0 | AA69: =X69 -> 0 | AB69: =AA69/$X$85 -> 0 | AC69: =AA69 -> 0 | AD69: =AC69/$X$85 -> 0 | AE69: =AC69 -> 0 | AF69: =AE69/$X$85 -> 0 | AG69: =AE69 -> 0 | AH69: =AG69/$X$85 -> 0 | AI69: =AG69 -> 0 | AJ69: =AI69/$X$85 -> 0
B70: Valet Trash Service | C70: ='IS (Combined)'!D30 -> -221 | D70: =+C70/$C$85 -> -0.00024071468 | E70: =I70/2 -> 0 | F70: =+E70/$E$85 -> 0 | G70: =C70-E70 -> -221 | I70: 0 | J70: =+I70/'[2]Data Entry'!$C$11 -> 0 | K70: =+I70/$I$85 -> 0 | L70: =+I70*(1+$L$8) -> 0 | M70: =+L70/'[2]Data Entry'!$C$11 -> 0 | N70: =+L70/$L$85 -> 0 | O70: =+L70*(1+$L$8) -> 0 | P70: =+O70/'[2]Data Entry'!$C$11 -> 0 | Q70: =+O70/$O$85 -> 0 | R70: =+O70*(1+$L$8) -> 0 | S70: =+R70/'[2]Data Entry'!$C$11 -> 0 | T70: =+R70/$R$85 -> 0 | U70: =+R70*(1+$L$8) -> 0 | V70: =+U70/'[2]Data Entry'!$C$11 -> 0 | W70: =+U70/$U$85 -> 0 | X70: =+U70*(1+$L$8) -> 0 | Y70: =+X70/'[2]Data Entry'!$C$11 -> 0 | Z70: =+X70/$X$85 -> 0 | AA70: =X70 -> 0 | AB70: =AA70/$X$85 -> 0 | AC70: =AA70 -> 0 | AD70: =AC70/$X$85 -> 0 | AE70: =AC70 -> 0 | AF70: =AE70/$X$85 -> 0 | AG70: =AE70 -> 0 | AH70: =AG70/$X$85 -> 0 | AI70: =AG70 -> 0 | AJ70: =AI70/$X$85 -> 0
B71: Vending Machine Income | C71: 0 | D71: =+C71/$C$85 -> 0 | E71: =I71/2 -> 0 | F71: =+E71/$E$85 -> 0 | G71: =C71-E71 -> 0 | I71: 0 | J71: =+I71/'[2]Data Entry'!$C$11 -> 0 | K71: =+I71/$I$85 -> 0 | L71: =+I71*(1+$L$8) -> 0 | M71: =+L71/'[2]Data Entry'!$C$11 -> 0 | N71: =+L71/$L$85 -> 0 | O71: =+L71*(1+$L$8) -> 0 | P71: =+O71/'[2]Data Entry'!$C$11 -> 0 | Q71: =+O71/$O$85 -> 0 | R71: =+O71*(1+$L$8) -> 0 | S71: =+R71/'[2]Data Entry'!$C$11 -> 0 | T71: =+R71/$R$85 -> 0 | U71: =+R71*(1+$L$8) -> 0 | V71: =+U71/'[2]Data Entry'!$C$11 -> 0 | W71: =+U71/$U$85 -> 0 | X71: =+U71*(1+$L$8) -> 0 | Y71: =+X71/'[2]Data Entry'!$C$11 -> 0 | Z71: =+X71/$X$85 -> 0 | AA71: =X71 -> 0 | AB71: =AA71/$X$85 -> 0 | AC71: =AA71 -> 0 | AD71: =AC71/$X$85 -> 0 | AE71: =AC71 -> 0 | AF71: =AE71/$X$85 -> 0 | AG71: =AE71 -> 0 | AH71: =AG71/$X$85 -> 0 | AI71: =AG71 -> 0 | AJ71: =AI71/$X$85 -> 0
B72: Washer/Dryer Rental Income | C72: 0 | D72: =+C72/$C$85 -> 0 | E72: =I72/2 -> 0 | F72: =+E72/$E$85 -> 0 | G72: =C72-E72 -> 0 | I72: 0 | J72: =+I72/'[2]Data Entry'!$C$11 -> 0 | K72: =+I72/$I$85 -> 0 | L72: =+I72*(1+$L$8) -> 0 | M72: =+L72/'[2]Data Entry'!$C$11 -> 0 | N72: =+L72/$L$85 -> 0 | O72: =+L72*(1+$L$8) -> 0 | P72: =+O72/'[2]Data Entry'!$C$11 -> 0 | Q72: =+O72/$O$85 -> 0 | R72: =+O72*(1+$L$8) -> 0 | S72: =+R72/'[2]Data Entry'!$C$11 -> 0 | T72: =+R72/$R$85 -> 0 | U72: =+R72*(1+$L$8) -> 0 | V72: =+U72/'[2]Data Entry'!$C$11 -> 0 | W72: =+U72/$U$85 -> 0 | X72: =+U72*(1+$L$8) -> 0 | Y72: =+X72/'[2]Data Entry'!$C$11 -> 0 | Z72: =+X72/$X$85 -> 0 | AA72: =X72 -> 0 | AB72: =AA72/$X$85 -> 0 | AC72: =AA72 -> 0 | AD72: =AC72/$X$85 -> 0 | AE72: =AC72 -> 0 | AF72: =AE72/$X$85 -> 0 | AG72: =AE72 -> 0 | AH72: =AG72/$X$85 -> 0 | AI72: =AG72 -> 0 | AJ72: =AI72/$X$85 -> 0
B73: Bad Debt Write Off - Other Income | C73: 0 | D73: =+C73/$C$85 -> 0 | E73: =I73/2 -> -3071 | F73: =+E73/$E$85 -> -0.0032431635 | G73: =C73-E73 -> 3071 | I73: -6142 | J73: =+I73/'[2]Data Entry'!$C$11 -> -74.902439 | K73: =+I73/$I$85 -> -0.0032431635 | L73: =+I73*(1+$L$8) -> -6203.42 | M73: =+L73/'[2]Data Entry'!$C$11 -> -75.651463 | N73: =+L73/$L$85 -> -0.0029376177 | O73: =+L73*(1+$L$8) -> -6265.4542 | P73: =+O73/'[2]Data Entry'!$C$11 -> -76.407978 | Q73: =+O73/$O$85 -> -0.0026890877 | R73: =+O73*(1+$L$8) -> -6328.1087 | S73: =+R73/'[2]Data Entry'!$C$11 -> -77.172058 | T73: =+R73/$R$85 -> -0.0025278322 | U73: =+R73*(1+$L$8) -> -6391.3898 | V73: =+U73/'[2]Data Entry'!$C$11 -> -77.943778 | W73: =+U73/$U$85 -> -0.0024828277 | X73: =+U73*(1+$L$8) -> -6455.3037 | Y73: =+X73/'[2]Data Entry'!$C$11 -> -78.723216 | Z73: =+X73/$X$85 -> -0.002438553 | AA73: =X73 -> -6455.3037 | AB73: =AA73/$X$85 -> -0.002438553 | AC73: =AA73 -> -6455.3037 | AD73: =AC73/$X$85 -> -0.002438553 | AE73: =AC73 -> -6455.3037 | AF73: =AE73/$X$85 -> -0.002438553 | AG73: =AE73 -> -6455.3037 | AH73: =AG73/$X$85 -> -0.002438553 | AI73: =AG73 -> -6455.3037 | AJ73: =AI73/$X$85 -> -0.002438553
B74: NSF Fees | C74: ='IS (Combined)'!D18 -> 1331.24 | D74: =+C74/$C$85 -> 0.0014499955 | E74: =I74/2 -> 725 | F74: =+E74/$E$85 -> 0.00076564426 | G74: =C74-E74 -> 606.24 | I74: 1450 | J74: =+I74/'[2]Data Entry'!$C$11 -> 17.682927 | K74: =+I74/$I$85 -> 0.00076564426 | L74: =+I74*(1+$L$8) -> 1464.5 | M74: =+L74/'[2]Data Entry'!$C$11 -> 17.859756 | N74: =+L74/$L$85 -> 0.00069351117 | O74: =+L74*(1+$L$8) -> 1479.145 | P74: =+O74/'[2]Data Entry'!$C$11 -> 18.038354 | Q74: =+O74/$O$85 -> 0.00063483835 | R74: =+O74*(1+$L$8) -> 1493.9364 | S74: =+R74/'[2]Data Entry'!$C$11 -> 18.218737 | T74: =+R74/$R$85 -> 0.00059676925 | U74: =+R74*(1+$L$8) -> 1508.8758 | V74: =+U74/'[2]Data Entry'!$C$11 -> 18.400925 | W74: =+U74/$U$85 -> 0.0005861446 | X74: =+U74*(1+$L$8) -> 1523.9646 | Y74: =+X74/'[2]Data Entry'!$C$11 -> 18.584934 | Z74: =+X74/$X$85 -> 0.00057569225 | AA74: =X74 -> 1523.9646 | AB74: =AA74/$X$85 -> 0.00057569225 | AC74: =AA74 -> 1523.9646 | AD74: =AC74/$X$85 -> 0.00057569225 | AE74: =AC74 -> 1523.9646 | AF74: =AE74/$X$85 -> 0.00057569225 | AG74: =AE74 -> 1523.9646 | AH74: =AG74/$X$85 -> 0.00057569225 | AI74: =AG74 -> 1523.9646 | AJ74: =AI74/$X$85 -> 0.00057569225
B75: Amenity Fee | C75: 0 | D75: =+C75/$C$85 -> 0 | E75: =I75/2 -> 0 | F75: =+E75/$E$85 -> 0 | G75: =C75-E75 -> 0 | I75: 0 | J75: =+I75/'[2]Data Entry'!$C$11 -> 0 | K75: =+I75/$I$85 -> 0 | L75: =+I75*(1+$L$8) -> 0 | M75: =+L75/'[2]Data Entry'!$C$11 -> 0 | N75: =+L75/$L$85 -> 0 | O75: =+L75*(1+$L$8) -> 0 | P75: =+O75/'[2]Data Entry'!$C$11 -> 0 | Q75: =+O75/$O$85 -> 0 | R75: =+O75*(1+$L$8) -> 0 | S75: =+R75/'[2]Data Entry'!$C$11 -> 0 | T75: =+R75/$R$85 -> 0 | U75: =+R75*(1+$L$8) -> 0 | V75: =+U75/'[2]Data Entry'!$C$11 -> 0 | W75: =+U75/$U$85 -> 0 | X75: =+U75*(1+$L$8) -> 0 | Y75: =+X75/'[2]Data Entry'!$C$11 -> 0 | Z75: =+X75/$X$85 -> 0
B76: Transfer Fee | C76: 0 | D76: =+C76/$C$85 -> 0 | E76: =I76/2 -> 0 | F76: =+E76/$E$85 -> 0 | G76: =C76-E76 -> 0 | I76: 0 | J76: =+I76/'[2]Data Entry'!$C$11 -> 0 | K76: =+I76/$I$85 -> 0 | L76: =+I76*(1+$L$8) -> 0 | M76: =+L76/'[2]Data Entry'!$C$11 -> 0 | N76: =+L76/$L$85 -> 0 | O76: =+L76*(1+$L$8) -> 0 | P76: =+O76/'[2]Data Entry'!$C$11 -> 0 | Q76: =+O76/$O$85 -> 0 | R76: =+O76*(1+$L$8) -> 0 | S76: =+R76/'[2]Data Entry'!$C$11 -> 0 | T76: =+R76/$R$85 -> 0 | U76: =+R76*(1+$L$8) -> 0 | V76: =+U76/'[2]Data Entry'!$C$11 -> 0 | W76: =+U76/$U$85 -> 0 | X76: =+U76*(1+$L$8) -> 0 | Y76: =+X76/'[2]Data Entry'!$C$11 -> 0 | Z76: =+X76/$X$85 -> 0
B77: Monthly Security Charge | C77: 0 | D77: =+C77/$C$85 -> 0 | E77: =I77/2 -> 534.5 | F77: =+E77/$E$85 -> 0.00056446463 | G77: =C77-E77 -> -534.5 | I77: 1069 | J77: =+I77/'[2]Data Entry'!$C$11 -> 13.036585 | K77: =+I77/$I$85 -> 0.00056446463 | L77: =+I77*(1+$L$8) -> 1079.69 | M77: =+L77/'[2]Data Entry'!$C$11 -> 13.166951 | N77: =+L77/$L$85 -> 0.00051128513 | O77: =+L77*(1+$L$8) -> 1090.4869 | P77: =+O77/'[2]Data Entry'!$C$11 -> 13.298621 | Q77: =+O77/$O$85 -> 0.0004680291 | R77: =+O77*(1+$L$8) -> 1101.3918 | S77: =+R77/'[2]Data Entry'!$C$11 -> 13.431607 | T77: =+R77/$R$85 -> 0.00043996298 | U77: =+R77*(1+$L$8) -> 1112.4057 | V77: =+U77/'[2]Data Entry'!$C$11 -> 13.565923 | W77: =+U77/$U$85 -> 0.00043213006 | X77: =+U77*(1+$L$8) -> 1123.5297 | Y77: =+X77/'[2]Data Entry'!$C$11 -> 13.701582 | Z77: =+X77/$X$85 -> 0.00042442415
B78: Tenant improvements | C78: ='IS (Combined)'!D34 -> 519.75 | D78: =+C78/$C$85 -> 0.00056611518 | E78: =I78/2 -> 0 | F78: =+E78/$E$85 -> 0 | G78: =C78-E78 -> 519.75 | I78: 0 | J78: =+I78/'[2]Data Entry'!$C$11 -> 0 | K78: =+I78/$I$85 -> 0 | L78: =+I78*(1+$L$8) -> 0 | M78: =+L78/'[2]Data Entry'!$C$11 -> 0 | N78: =+L78/$L$85 -> 0 | O78: =+L78*(1+$L$8) -> 0 | P78: =+O78/'[2]Data Entry'!$C$11 -> 0 | Q78: =+O78/$O$85 -> 0 | R78: =+O78*(1+$L$8) -> 0 | S78: =+R78/'[2]Data Entry'!$C$11 -> 0 | T78: =+R78/$R$85 -> 0 | U78: =+R78*(1+$L$8) -> 0 | V78: =+U78/'[2]Data Entry'!$C$11 -> 0 | W78: =+U78/$U$85 -> 0 | X78: =+U78*(1+$L$8) -> 0 | Y78: =+X78/'[2]Data Entry'!$C$11 -> 0 | Z78: =+X78/$X$85 -> 0
B79: Other | C79: ='IS (Combined)'!D23 -> 300.32 | D79: =+C79/$C$85 -> 0.00032711056 | E79: =I79/2 -> 0 | F79: =+E79/$E$85 -> 0 | G79: =C79-E79 -> 300.32 | I79: 0 | J79: =+I79/'[2]Data Entry'!$C$11 -> 0 | K79: =+I79/$I$85 -> 0 | L79: =+I79*(1+$L$8) -> 0 | M79: =+L79/'[2]Data Entry'!$C$11 -> 0 | N79: =+L79/$L$85 -> 0 | O79: =+L79*(1+$L$8) -> 0 | P79: =+O79/'[2]Data Entry'!$C$11 -> 0 | Q79: =+O79/$O$85 -> 0 | R79: =+O79*(1+$L$8) -> 0 | S79: =+R79/'[2]Data Entry'!$C$11 -> 0 | T79: =+R79/$R$85 -> 0 | U79: =+R79*(1+$L$8) -> 0 | V79: =+U79/'[2]Data Entry'!$C$11 -> 0 | W79: =+U79/$U$85 -> 0 | X79: =+U79*(1+$L$8) -> 0 | Y79: =+X79/'[2]Data Entry'!$C$11 -> 0 | Z79: =+X79/$X$85 -> 0
B80: Other | C80: 0 | D80: =+C80/$C$85 -> 0 | E80: =I80/2 -> 0 | F80: =+E80/$E$85 -> 0 | G80: =C80-E80 -> 0 | I80: 0 | J80: =+I80/'[2]Data Entry'!$C$11 -> 0 | K80: =+I80/$I$85 -> 0 | L80: =+I80*(1+$L$8) -> 0 | M80: =+L80/'[2]Data Entry'!$C$11 -> 0 | N80: =+L80/$L$85 -> 0 | O80: =+L80*(1+$L$8) -> 0 | P80: =+O80/'[2]Data Entry'!$C$11 -> 0 | Q80: =+O80/$O$85 -> 0 | R80: =+O80*(1+$L$8) -> 0 | S80: =+R80/'[2]Data Entry'!$C$11 -> 0 | T80: =+R80/$R$85 -> 0 | U80: =+R80*(1+$L$8) -> 0 | V80: =+U80/'[2]Data Entry'!$C$11 -> 0 | W80: =+U80/$U$85 -> 0 | X80: =+U80*(1+$L$8) -> 0 | Y80: =+X80/'[2]Data Entry'!$C$11 -> 0 | Z80: =+X80/$X$85 -> 0
B81: Other | C81: 0 | D81: =+C81/$C$85 -> 0 | E81: =I81/2 -> 0 | F81: =+E81/$E$85 -> 0 | G81: =C81-E81 -> 0 | I81: 0 | J81: =+I81/'[2]Data Entry'!$C$11 -> 0 | K81: =+I81/$I$85 -> 0 | L81: =+I81*(1+$L$8) -> 0 | M81: =+L81/'[2]Data Entry'!$C$11 -> 0 | N81: =+L81/$L$85 -> 0 | O81: =+L81*(1+$L$8) -> 0 | P81: =+O81/'[2]Data Entry'!$C$11 -> 0 | Q81: =+O81/$O$85 -> 0 | R81: =+O81*(1+$L$8) -> 0 | S81: =+R81/'[2]Data Entry'!$C$11 -> 0 | T81: =+R81/$R$85 -> 0 | U81: =+R81*(1+$L$8) -> 0 | V81: =+U81/'[2]Data Entry'!$C$11 -> 0 | W81: =+U81/$U$85 -> 0 | X81: =+U81*(1+$L$8) -> 0 | Y81: =+X81/'[2]Data Entry'!$C$11 -> 0 | Z81: =+X81/$X$85 -> 0
B82: Other | C82: 0 | D82: =+C82/$C$85 -> 0 | E82: =I82/2 -> 0 | F82: =+E82/$E$85 -> 0 | G82: =C82-E82 -> 0 | I82: 0 | J82: =+I82/'[2]Data Entry'!$C$11 -> 0 | K82: =+I82/$I$85 -> 0 | L82: =+I82*(1+$L$8) -> 0 | M82: =+L82/'[2]Data Entry'!$C$11 -> 0 | N82: =+L82/$L$85 -> 0 | O82: =+L82*(1+$L$8) -> 0 | P82: =+O82/'[2]Data Entry'!$C$11 -> 0 | Q82: =+O82/$O$85 -> 0 | R82: =+O82*(1+$L$8) -> 0 | S82: =+R82/'[2]Data Entry'!$C$11 -> 0 | T82: =+R82/$R$85 -> 0 | U82: =+R82*(1+$L$8) -> 0 | V82: =+U82/'[2]Data Entry'!$C$11 -> 0 | W82: =+U82/$U$85 -> 0 | X82: =+U82*(1+$L$8) -> 0 | Y82: =+X82/'[2]Data Entry'!$C$11 -> 0 | Z82: =+X82/$X$85 -> 0
B83: Total Other Income | C83: =SUM(C37:C82) -> 87785.74 | D83: =+C83/$C$85 -> 0.095616817 | E83: =SUM(E37:E82) -> 52653 | F83: =+E83/$E$85 -> 0.055604782 | G83: =SUM(G37:G82) -> 35132.74 | I83: =SUM(I37:I82) -> 105306 | J83: =+I83/'[2]Data Entry'!$C$11 -> 1284.2195 | K83: =+I83/$I$85 -> 0.055604782 | L83: =SUM(L37:L82) -> 157834.34 | M83: =+L83/'[2]Data Entry'!$C$11 -> 1924.809 | N83: =+L83/$L$85 -> 0.07474215 | O83: =SUM(O37:O82) -> 209740.65 | P83: =+O83/'[2]Data Entry'!$C$11 -> 2557.8128 | Q83: =+O83/$O$85 -> 0.090019174 | R83: =SUM(R37:R82) -> 211838.06 | S83: =+R83/'[2]Data Entry'!$C$11 -> 2583.391 | T83: =+R83/$R$85 -> 0.084621029 | U83: =SUM(U37:U82) -> 213956.44 | V83: =U83/'[2]Data Entry'!$C$11 -> 2609.2249 | W83: =+U83/$U$85 -> 0.08311447 | X83: =SUM(X37:X82) -> 216096 | Y83: =X83/'[2]Data Entry'!$C$11 -> 2635.3171 | Z83: =+X83/$X$85 -> 0.081632341 | AA83: =X83 -> 216096 | AB83: =AA83/$X$85 -> 0.081632341 | AC83: =AA83 -> 216096 | AD83: =AC83/$X$85 -> 0.081632341 | AE83: =AC83 -> 216096 | AF83: =AE83/$X$85 -> 0.081632341 | AG83: =AE83 -> 216096 | AH83: =AG83/$X$85 -> 0.081632341 | AI83: =AG83 -> 216096 | AJ83: =AI83/$X$85 -> 0.081632341
B85: Total Income | C85: =+C34+C83 -> 918099.38 | D85: =+C85/C85 -> 1 | E85: =+E34+E83 -> 946914.96 | F85: =+E85/$E$85 -> 1 | G85: =+G34+G83 -> -28815.58 | I85: =+I34+I83 -> 1893829.9 | J85: =+I85/'[2]Data Entry'!$C$11 -> 23095.487 | K85: =+I85/$I$85 -> 1 | L85: =+L34+L83 -> 2111718 | M85: =+L85/'[2]Data Entry'!$C$11 -> 25752.658 | N85: =+L85/$L$85 -> 1 | O85: =+O34+O83 -> 2329955.3 | P85: =+O85/'[2]Data Entry'!$C$11 -> 28414.089 | Q85: =+O85/$O$85 -> 1 | R85: =+R34+R83 -> 2503373.7 | S85: =+R85/'[2]Data Entry'!$C$11 -> 30528.948 | T85: =+R85/$R$85 -> 1 | U85: =+U34+U83 -> 2574238.2 | V85: =+U85/'[2]Data Entry'!$C$11 -> 31393.148 | W85: =+U85/$U$85 -> 1 | X85: =+X34+X83 -> 2647186.2 | Y85: =+X85/'[2]Data Entry'!$C$11 -> 32282.758 | Z85: =+X85/$X$85 -> 1 | AA85: =SUM(AA56:AA83) -> 2798632.5 | AB85: =AA85/$X$85 -> 1.0572103 | AC85: =SUM(AC56:AC83) -> 2846706.8 | AD85: =AC85/$X$85 -> 1.0753708 | AE85: =SUM(AE56:AE83) -> 2895742.4 | AF85: =AE85/$X$85 -> 1.0938945 | AG85: =SUM(AG56:AG83) -> 2945758.5 | AH85: =AG85/$X$85 -> 1.1127886 | AI85: =SUM(AI56:AI83) -> 2996774.7 | AJ85: =AI85/$X$85 -> 1.1320604
B87: EXPENSES:
B88: Advertising & Promotion | C88: ='IS (Combined)'!D78 -> 6526.11 | D88: =+C88/$C$85 -> 0.0071082828 | E88: =I88/2 -> 2050 | F88: =+E88/E$85 -> 0.0021649251 | G88: =C88-E88 -> 4476.11 | I88: 4100 | J88: =+I88/'[2]Data Entry'!$C$11 -> 50 | K88: =+I88/I$85 -> 0.0021649251 | L88: =(1+$L$9)*+I88 -> 4223 | M88: =+L88/'[2]Data Entry'!$C$11 -> 51.5 | N88: =+L88/$L$85 -> 0.0019997936 | O88: =(1+$L$9)*+L88 -> 4349.69 | P88: =+O88/'[2]Data Entry'!$C$11 -> 53.045 | Q88: =+O88/$O$85 -> 0.0018668555 | R88: =(1+$L$9)*+O88 -> 4480.1807 | S88: =+R88/'[2]Data Entry'!$C$11 -> 54.63635 | T88: =+R88/$R$85 -> 0.0017896572 | U88: =(1+$L$9)*+R88 -> 4614.5861 | V88: =+U88/'[2]Data Entry'!$C$11 -> 56.275441 | W88: =+U88/$U$85 -> 0.0017926026 | X88: =(1+$L$9)*+U88 -> 4753.0237 | Y88: =+X88/'[2]Data Entry'!$C$11 -> 57.963704 | Z88: =+X88/$X$85 -> 0.0017955003
B89: Contract Services | E89: =I89/2 -> 0 | G89: =C89-E89 -> 0
B90: CS - Cleaning - Common Area | C90: ='IS (Combined)'!D42 -> 9479.81 | D90: =+C90/$C$85 -> 0.010325473 | E90: =I90/2 -> 2400 | F90: =+E90/E$85 -> 0.0025345465 | G90: =C90-E90 -> 7079.81 | I90: 4800 | J90: =+I90/'[2]Data Entry'!$C$11 -> 58.536585 | K90: =+I90/I$85 -> 0.0025345465 | L90: =(1+$L$9)*+I90 -> 4944 | M90: =+L90/'[2]Data Entry'!$C$11 -> 60.292683 | N90: =+L90/$L$85 -> 0.0023412217 | O90: =(1+$L$9)*+L90 -> 5092.32 | P90: =+O90/'[2]Data Entry'!$C$11 -> 62.101463 | Q90: =+O90/$O$85 -> 0.002185587 | R90: =(1+$L$9)*+O90 -> 5245.0896 | S90: =+R90/'[2]Data Entry'!$C$11 -> 63.964507 | T90: =+R90/$R$85 -> 0.0020952084 | U90: =(1+$L$9)*+R90 -> 5402.4423 | V90: =+U90/'[2]Data Entry'!$C$11 -> 65.883443 | W90: =+U90/$U$85 -> 0.0020986567 | X90: =(1+$L$9)*+U90 -> 5564.5156 | Y90: =+X90/'[2]Data Entry'!$C$11 -> 67.859946 | Z90: =+X90/$X$85 -> 0.0021020492
B91: CS - Landscaping Maintenance | C91: ='IS (Combined)'!D48 -> 2743 | D91: =+C91/$C$85 -> 0.002987694 | E91: =I91/2 -> 4890 | F91: =+E91/E$85 -> 0.0051641385 | G91: =C91-E91 -> -2147 | I91: 9780 | J91: =+I91/'[2]Data Entry'!$C$11 -> 119.26829 | K91: =+I91/I$85 -> 0.0051641385 | L91: =(1+$L$9)*+I91 -> 10073.4 | M91: =+L91/'[2]Data Entry'!$C$11 -> 122.84634 | N91: =+L91/$L$85 -> 0.0047702393 | O91: =(1+$L$9)*+L91 -> 10375.602 | P91: =+O91/'[2]Data Entry'!$C$11 -> 126.53173 | Q91: =+O91/$O$85 -> 0.0044531334 | R91: =(1+$L$9)*+O91 -> 10686.87 | S91: =+R91/'[2]Data Entry'!$C$11 -> 130.32768 | T91: =+R91/$R$85 -> 0.0042689871 | U91: =(1+$L$9)*+R91 -> 11007.476 | V91: =+U91/'[2]Data Entry'!$C$11 -> 134.23751 | W91: =+U91/$U$85 -> 0.0042760131 | X91: =(1+$L$9)*+U91 -> 11337.7 | Y91: =+X91/'[2]Data Entry'!$C$11 -> 138.26464 | Z91: =+X91/$X$85 -> 0.0042829252
B92: CS - Pest Control | C92: ='IS (Combined)'!D47 -> 173.35 | D92: =+C92/$C$85 -> 0.00018881398 | E92: =I92/2 -> 1081.5 | F92: =+E92/E$85 -> 0.00114213 | G92: =C92-E92 -> -908.15 | I92: 2163 | J92: =+I92/'[2]Data Entry'!$C$11 -> 26.378049 | K92: =+I92/I$85 -> 0.00114213 | L92: =(1+$L$9)*+I92 -> 2227.89 | M92: =+L92/'[2]Data Entry'!$C$11 -> 27.16939 | N92: =+L92/$L$85 -> 0.001055013 | O92: =(1+$L$9)*+L92 -> 2294.7267 | P92: =+O92/'[2]Data Entry'!$C$11 -> 27.984472 | Q92: =+O92/$O$85 -> 0.00098488013 | R92: =(1+$L$9)*+O92 -> 2363.5685 | S92: =+R92/'[2]Data Entry'!$C$11 -> 28.824006 | T92: =+R92/$R$85 -> 0.00094415327 | U92: =(1+$L$9)*+R92 -> 2434.4756 | V92: =+U92/'[2]Data Entry'!$C$11 -> 29.688726 | W92: =+U92/$U$85 -> 0.00094570719 | X92: =(1+$L$9)*+U92 -> 2507.5098 | Y92: =+X92/'[2]Data Entry'!$C$11 -> 30.579388 | Z92: =+X92/$X$85 -> 0.00094723591
B93: CS - Pool Expense | C93: ='IS (Combined)'!D46 -> 3117.08 | D93: =+C93/$C$85 -> 0.0033951444 | E93: =I93/2 -> 2100 | F93: =+E93/E$85 -> 0.0022177282 | G93: =C93-E93 -> 1017.08 | I93: 4200 | J93: =+I93/'[2]Data Entry'!$C$11 -> 51.219512 | K93: =+I93/I$85 -> 0.0022177282 | L93: =(1+$L$9)*+I93 -> 4326 | M93: =+L93/'[2]Data Entry'!$C$11 -> 52.756098 | N93: =+L93/$L$85 -> 0.002048569 | O93: =(1+$L$9)*+L93 -> 4455.78 | P93: =+O93/'[2]Data Entry'!$C$11 -> 54.33878 | Q93: =+O93/$O$85 -> 0.0019123886 | R93: =(1+$L$9)*+O93 -> 4589.4534 | S93: =+R93/'[2]Data Entry'!$C$11 -> 55.968944 | T93: =+R93/$R$85 -> 0.0018333073 | U93: =(1+$L$9)*+R93 -> 4727.137 | V93: =+U93/'[2]Data Entry'!$C$11 -> 57.648012 | W93: =+U93/$U$85 -> 0.0018363246 | X93: =(1+$L$9)*+U93 -> 4868.9511 | Y93: =+X93/'[2]Data Entry'!$C$11 -> 59.377453 | Z93: =+X93/$X$85 -> 0.001839293
B94: CS - Elevator | C94: ='IS (Combined)'!D45 -> 3770 | D94: =+C94/$C$85 -> 0.0041063093 | E94: =I94/2 -> 1440 | F94: =+E94/E$85 -> 0.0015207279 | G94: =C94-E94 -> 2330 | I94: 2880 | J94: =+I94/'[2]Data Entry'!$C$11 -> 35.121951 | K94: =+I94/I$85 -> 0.0015207279 | L94: =(1+$L$9)*+I94 -> 2966.4 | M94: =+L94/'[2]Data Entry'!$C$11 -> 36.17561 | N94: =+L94/$L$85 -> 0.001404733 | O94: =(1+$L$9)*+L94 -> 3055.392 | P94: =+O94/'[2]Data Entry'!$C$11 -> 37.260878 | Q94: =+O94/$O$85 -> 0.0013113522 | R94: =(1+$L$9)*+O94 -> 3147.0538 | S94: =+R94/'[2]Data Entry'!$C$11 -> 38.378704 | T94: =+R94/$R$85 -> 0.001257125 | U94: =(1+$L$9)*+R94 -> 3241.4654 | V94: =+U94/'[2]Data Entry'!$C$11 -> 39.530066 | W94: =+U94/$U$85 -> 0.001259194 | X94: =(1+$L$9)*+U94 -> 3338.7093 | Y94: =+X94/'[2]Data Entry'!$C$11 -> 40.715967 | Z94: =+X94/$X$85 -> 0.0012612295
B95: CS - Security | C95: 0 | D95: =+C95/$C$85 -> 0 | E95: =I95/2 -> 0 | F95: =+E95/E$85 -> 0 | G95: =C95-E95 -> 0 | I95: 0 | J95: =+I95/'[2]Data Entry'!$C$11 -> 0 | K95: =+I95/I$85 -> 0 | L95: =(1+$L$9)*+I95 -> 0 | M95: =+L95/'[2]Data Entry'!$C$11 -> 0 | N95: =+L95/$L$85 -> 0 | O95: =(1+$L$9)*+L95 -> 0 | P95: =+O95/'[2]Data Entry'!$C$11 -> 0 | Q95: =+O95/$O$85 -> 0 | R95: =(1+$L$9)*+O95 -> 0 | S95: =+R95/'[2]Data Entry'!$C$11 -> 0 | T95: =+R95/$R$85 -> 0 | U95: =(1+$L$9)*+R95 -> 0 | V95: =+U95/'[2]Data Entry'!$C$11 -> 0 | W95: =+U95/$U$85 -> 0 | X95: =(1+$L$9)*+U95 -> 0 | Y95: =+X95/'[2]Data Entry'!$C$11 -> 0 | Z95: =+X95/$X$85 -> 0
B96: CS - Valet Trash | C96: 0 | D96: =+C96/$C$85 -> 0 | E96: =I96/2 -> 0 | F96: =+E96/E$85 -> 0 | G96: =C96-E96 -> 0 | I96: 0 | J96: =+I96/'[2]Data Entry'!$C$11 -> 0 | K96: =+I96/I$85 -> 0 | L96: =(1+$L$9)*+I96 -> 0 | M96: =+L96/'[2]Data Entry'!$C$11 -> 0 | N96: =+L96/$L$85 -> 0 | O96: =(1+$L$9)*+L96 -> 0 | P96: =+O96/'[2]Data Entry'!$C$11 -> 0 | Q96: =+O96/$O$85 -> 0 | R96: =(1+$L$9)*+O96 -> 0 | S96: =+R96/'[2]Data Entry'!$C$11 -> 0 | T96: =+R96/$R$85 -> 0 | U96: =(1+$L$9)*+R96 -> 0 | V96: =+U96/'[2]Data Entry'!$C$11 -> 0 | W96: =+U96/$U$85 -> 0 | X96: =(1+$L$9)*+U96 -> 0 | Y96: =+X96/'[2]Data Entry'!$C$11 -> 0 | Z96: =+X96/$X$85 -> 0
B97: CS - Trash Removal | C97: ='IS (Combined)'!D70 -> 1656 | D97: =+C97/$C$85 -> 0.0018037263 | E97: =I97/2 -> 22565 | F97: =+E97/E$85 -> 0.023830017 | G97: =C97-E97 -> -20909 | I97: 45130 | J97: =+I97/'[2]Data Entry'!$C$11 -> 550.36585 | K97: =+I97/I$85 -> 0.023830017 | L97: =(1+$L$9)*+I97 -> 46483.9 | M97: =+L97/'[2]Data Entry'!$C$11 -> 566.87683 | N97: =+L97/$L$85 -> 0.022012362 | O97: =(1+$L$9)*+L97 -> 47878.417 | P97: =+O97/'[2]Data Entry'!$C$11 -> 583.88313 | Q97: =+O97/$O$85 -> 0.020549071 | R97: =(1+$L$9)*+O97 -> 49314.77 | S97: =+R97/'[2]Data Entry'!$C$11 -> 601.39963 | T97: =+R97/$R$85 -> 0.019699324 | U97: =(1+$L$9)*+R97 -> 50794.213 | V97: =+U97/'[2]Data Entry'!$C$11 -> 619.44162 | W97: =+U97/$U$85 -> 0.019731746 | X97: =(1+$L$9)*+U97 -> 52318.039 | Y97: =+X97/'[2]Data Entry'!$C$11 -> 638.02487 | Z97: =+X97/$X$85 -> 0.019763642
B98: Insurance Expense - Property/Liab | E98: =I98/2 -> 0 | G98: =C98-E98 -> 0
B99: INS - Property Insurance | C99: ='IS (Combined)'!D79 -> 62775.22 | D99: =+C99/$C$85 -> 0.06837519 | E99: =I99/2 -> 61500 | F99: =+E99/E$85 -> 0.064947754 | G99: =C99-E99 -> 1275.22 | I99: 123000 | J99: 1470 | K99: =+I99/I$85 -> 0.064947754 | L99: =(1+$L$9)*+I99 -> 126690 | M99: =+L99/'[2]Data Entry'!$C$11 -> 1545 | N99: =+L99/$L$85 -> 0.059993807 | O99: =(1+$L$9)*+L99 -> 130490.7 | P99: =+O99/'[2]Data Entry'!$C$11 -> 1591.35 | Q99: =+O99/$O$85 -> 0.056005666 | R99: =(1+$L$9)*+O99 -> 134405.42 | S99: =+R99/'[2]Data Entry'!$C$11 -> 1639.0905 | T99: =+R99/$R$85 -> 0.053689715 | U99: =(1+$L$9)*+R99 -> 138437.58 | V99: =+U99/'[2]Data Entry'!$C$11 -> 1688.2632 | W99: =+U99/$U$85 -> 0.053778079 | X99: =(1+$L$9)*+U99 -> 142590.71 | Y99: =+X99/'[2]Data Entry'!$C$11 -> 1738.9111 | Z99: =+X99/$X$85 -> 0.05386501
B100: INS - Flood Insurance | C100: 0 | D100: =+C100/$C$85 -> 0 | E100: =I100/2 -> 0 | F100: =+E100/E$85 -> 0 | G100: =C100-E100 -> 0 | I100: 0 | J100: =+I100/'[2]Data Entry'!$C$11 -> 0 | K100: =+I100/I$85 -> 0 | L100: =(1+$L$9)*+I100 -> 0 | M100: =+L100/'[2]Data Entry'!$C$11 -> 0 | N100: =+L100/$L$85 -> 0 | O100: =(1+$L$9)*+L100 -> 0 | P100: =+O100/'[2]Data Entry'!$C$11 -> 0 | Q100: =+O100/$O$85 -> 0 | R100: =(1+$L$9)*+O100 -> 0 | S100: =+R100/'[2]Data Entry'!$C$11 -> 0 | T100: =+R100/$R$85 -> 0 | U100: =(1+$L$9)*+R100 -> 0 | V100: =+U100/'[2]Data Entry'!$C$11 -> 0 | W100: =+U100/$U$85 -> 0 | X100: =(1+$L$9)*+U100 -> 0 | Y100: =+X100/'[2]Data Entry'!$C$11 -> 0 | Z100: =+X100/$X$85 -> 0
B101: INS - Other (Gen Liab) | C101: 0 | D101: =+C101/$C$85 -> 0 | E101: =I101/2 -> 0 | F101: =+E101/E$85 -> 0 | G101: =C101-E101 -> 0 | J101: =+I101/'[2]Data Entry'!$C$11 -> 0 | K101: =+I101/I$85 -> 0 | L101: =(1+$L$9)*+I101 -> 0 | M101: =+L101/'[2]Data Entry'!$C$11 -> 0 | N101: =+L101/$L$85 -> 0 | O101: =(1+$L$9)*+L101 -> 0 | P101: =+O101/'[2]Data Entry'!$C$11 -> 0 | Q101: =+O101/$O$85 -> 0 | R101: =(1+$L$9)*+O101 -> 0 | S101: =+R101/'[2]Data Entry'!$C$11 -> 0 | T101: =+R101/$R$85 -> 0 | U101: =(1+$L$9)*+R101 -> 0 | V101: =+U101/'[2]Data Entry'!$C$11 -> 0 | W101: =+U101/$U$85 -> 0 | X101: =(1+$L$9)*+U101 -> 0 | Y101: =+X101/'[2]Data Entry'!$C$11 -> 0 | Z101: =+X101/$X$85 -> 0
B102: Property Management Fees | C102: ='IS (Combined)'!D57 -> 1663.59 | D102: =+C102/$C$85 -> 0.0018119934 | E102: =I102/2 -> 52080.323 | F102: =+E102/E$85 -> 0.055 | G102: =C102-E102 -> -50416.733 | I102: =+I85*'[2]Data Entry'!$C$32 -> 104160.65 | J102: =+I102/'[2]Data Entry'!$C$11 -> 1270.2518 | K102: =+I102/I$85 -> 0.055 | L102: =+L85*'[2]Data Entry'!$C$32 -> 116144.49 | M102: =+L102/'[2]Data Entry'!$C$11 -> 1416.3962 | N102: =+L102/$L$85 -> 0.055 | O102: =+O85*'[2]Data Entry'!$C$32 -> 128147.54 | P102: =+O102/'[2]Data Entry'!$C$11 -> 1562.7749 | Q102: =+O102/$O$85 -> 0.055 | R102: =+R85*'[2]Data Entry'!$C$32 -> 137685.55 | S102: =+R102/'[2]Data Entry'!$C$11 -> 1679.0921 | T102: =+R102/$R$85 -> 0.055 | U102: =+U85*'[2]Data Entry'!$C$32 -> 141583.1 | V102: =+U102/'[2]Data Entry'!$C$11 -> 1726.6232 | W102: =+U102/$U$85 -> 0.055 | X102: =+X85*'[2]Data Entry'!$C$32 -> 145595.24 | Y102: =+X102/'[2]Data Entry'!$C$11 -> 1775.5517 | Z102: =+X102/$X$85 -> 0.055
B103: Misc. Expense | C103: 0 | D103: =+C103/$C$85 -> 0 | E103: =I103/2 -> 30 | F103: =+E103/E$85 -> 3.1681831e-05 | G103: =C103-E103 -> -30 | I103: 60 | J103: =+I103/'[2]Data Entry'!$C$11 -> 0.73170732 | K103: =+I103/I$85 -> 3.1681831e-05 | L103: =(1+$L$9)*+I103 -> 61.8 | M103: =+L103/'[2]Data Entry'!$C$11 -> 0.75365854 | N103: =+L103/$L$85 -> 2.9265272e-05 | O103: =(1+$L$9)*+L103 -> 63.654 | P103: =+O103/'[2]Data Entry'!$C$11 -> 0.77626829 | Q103: =+O103/$O$85 -> 2.7319837e-05 | R103: =(1+$L$9)*+O103 -> 65.56362 | S103: =+R103/'[2]Data Entry'!$C$11 -> 0.79955634 | T103: =+R103/$R$85 -> 2.6190105e-05 | U103: =(1+$L$9)*+R103 -> 67.530529 | V103: =+U103/'[2]Data Entry'!$C$11 -> 0.82354303 | W103: =+U103/$U$85 -> 2.6233209e-05 | X103: =(1+$L$9)*+U103 -> 69.556444 | Y103: =+X103/'[2]Data Entry'!$C$11 -> 0.84824932 | Z103: =+X103/$X$85 -> 2.6275615e-05
B104: Payroll & Related Expenses | C104: 0 | D104: =+C104/$C$85 -> 0 | E104: =I104/2 -> 0 | F104: =+E104/E$85 -> 0 | G104: =C104-E104 -> 0 | I104: ='[2]Admin - Payroll - RE Taxes'!E22 -> 0 | J104: =+I104/'[2]Data Entry'!$C$11 -> 0 | K104: =+I104/I$85 -> 0 | L104: =(1+$L$9)*+I104 -> 0 | M104: =+L104/'[2]Data Entry'!$C$11 -> 0 | N104: =+L104/$L$85 -> 0 | O104: =(1+$L$9)*+L104 -> 0 | P104: =+O104/'[2]Data Entry'!$C$11 -> 0 | Q104: =+O104/$O$85 -> 0 | R104: =(1+$L$9)*+O104 -> 0 | S104: =+R104/'[2]Data Entry'!$C$11 -> 0 | T104: =+R104/$R$85 -> 0 | U104: =(1+$L$9)*+R104 -> 0 | V104: =+U104/'[2]Data Entry'!$C$11 -> 0 | W104: =+U104/$U$85 -> 0 | X104: =(1+$L$9)*+U104 -> 0 | Y104: =+X104/'[2]Data Entry'!$C$11 -> 0 | Z104: =+X104/$X$85 -> 0
B105: Repairs & Maintenance | C105: ='IS (Combined)'!D66 -> 42569.96 | D105: =+C105/$C$85 -> 0.046367486 | E105: =I105/2 -> 6765 | F105: =+E105/E$85 -> 0.007144253 | G105: =C105-E105 -> 35804.96 | I105: =+'[2]Data Entry'!$C$11*J105 -> 13530 | J105: 165 | K105: =+I105/I$85 -> 0.007144253 | L105: =(1+$L$9)*+I105 -> 13935.9 | M105: =+L105/'[2]Data Entry'!$C$11 -> 169.95 | N105: =+L105/$L$85 -> 0.0065993188 | O105: =(1+$L$9)*+L105 -> 14353.977 | P105: =+O105/'[2]Data Entry'!$C$11 -> 175.0485 | Q105: =+O105/$O$85 -> 0.0061606233 | R105: =(1+$L$9)*+O105 -> 14784.596 | S105: =+R105/'[2]Data Entry'!$C$11 -> 180.29996 | T105: =+R105/$R$85 -> 0.0059058686 | U105: =(1+$L$9)*+R105 -> 15228.134 | V105: =+U105/'[2]Data Entry'!$C$11 -> 185.70895 | W105: =+U105/$U$85 -> 0.0059155887 | X105: =(1+$L$9)*+U105 -> 15684.978 | Y105: =+X105/'[2]Data Entry'!$C$11 -> 191.28022 | Z105: =+X105/$X$85 -> 0.0059251511
B106: Unit Turn Costs | C106: 0 | D106: =+C106/$C$85 -> 0 | E106: =I106/2 -> 18450 | F106: =+E106/E$85 -> 0.019484326 | G106: =C106-E106 -> -18450 | I106: =+'[2]Data Entry'!$C$11*J106 -> 36900 | J106: 450 | K106: =+I106/I$85 -> 0.019484326 | L106: =(1+$L$9)*+I106 -> 38007 | M106: =+L106/'[2]Data Entry'!$C$11 -> 463.5 | N106: =+L106/$L$85 -> 0.017998142 | O106: =(1+$L$9)*+L106 -> 39147.21 | P106: =+O106/'[2]Data Entry'!$C$11 -> 477.405 | Q106: =+O106/$O$85 -> 0.0168017 | R106: =(1+$L$9)*+O106 -> 40321.626 | S106: =+R106/'[2]Data Entry'!$C$11 -> 491.72715 | T106: =+R106/$R$85 -> 0.016106914 | U106: =(1+$L$9)*+R106 -> 41531.275 | V106: =+U106/'[2]Data Entry'!$C$11 -> 506.47896 | W106: =+U106/$U$85 -> 0.016133424 | X106: =(1+$L$9)*+U106 -> 42777.213 | Y106: =+X106/'[2]Data Entry'!$C$11 -> 521.67333 | Z106: =+X106/$X$85 -> 0.016159503
...

Sheet BS & IS (Combined)
A1: Allaire on 41st top level
A2: Unaudited Consolidated Balance Sheet
A3: As of 9/30/2025
A6: ASSETS
A7: Cash and Cash Equivalents | B7: ='TB Combined'!H5+'TB Combined'!H6 -> 1178469.8
A8: Accounts Receivable | B8: ='TB Combined'!H7 -> 49276.86
A9: Prepaid Insurance | B9: ='TB Combined'!H10 -> 60248.17
A10: Prepaid Interest | B10: ='TB Combined'!H11 -> 0
A11: Prepaid Other | B11: ='TB Combined'!H12 -> 0
A12: Fixed Assets, Net | B12: ='TB Combined'!H13 -> 17627868
A13: Capitalized Loan Costs, Net | B13: ='TB Combined'!H14 -> 168204.2
A14: Deposits in Escrow | B14: ='TB Combined'!H15 -> 99209.46
A15: Property Tax in Escrow | B15: ='TB Combined'!H16 -> 215081.24
A16: Other Assets | B16: ='TB Combined'!H17 -> 0
A17: TOTAL ASSETS | B17: =SUM(B7:B16) -> 19398358
A19: LIABILITIES AND EQUITY
A20: Liabilities
A21: Accounts Payable | B21: =-'TB Combined'!H18-'TB Combined'!H19 -> 20779.49
A22: Security Deposits | B22: =-'TB Combined'!H8-'TB Combined'!H9 -> 110900.39
A23: Property Taxes Payable | B23: =-'TB Combined'!H20 -> 177461.29
A24: Management Fee Payable | B24: =-'TB Combined'!H21 -> 36450
A25: Notes Payable | B25: =-'TB Combined'!H22 -> 12180000
A26: Other Liabilities
A27: Total Liabilities | B27: =SUM(B21:B26) -> 12525591
A28: Equity
A29: Members Equity | B29: =-'TB Combined'!H23 -> 7290000
A30: Current Year Net Income | B30: =B98 -> -363004.67
A31: Accumulated Earnings & Profits
A32: Total Equity | B32: =SUM(B29:B31) -> 6926995.3
A33: TOTAL LIABILITIES AND EQUITY | B33: =(B27)+(B32) -> 19452586
B36: =B33-B17 -> 54228.31
A41: =A1 -> Allaire on 41st top level
A42: Unaudited Consolidated Income Statement
A43: April 9, 2025 through September 30, 2025
A45: REVENUES
A46: Rent Income | B46: =-'TB Combined'!H25-'TB Combined'!H26-'TB Combined'!H27 -> 884541.96
A47: Other Income | B47: =-SUM('TB Combined'!H28:H44) -> 87785.74
A48: Gross Operating Profit | B48: =SUM(B46:B47) -> 972327.7
A50: Supplies - Cleaning and Maitenance | B50: =-'TB Combined'!H47-'TB Combined'!H46 -> -339.91
A51: Cleaning and Maintenance -Other | B51: =-'TB Combined'!H48 -> -9139.9
A52: Permits & Licenses | B52: =-'TB Combined'!H49 -> -1094.3
A53: Elevator | B53: =-'TB Combined'!H50 -> -3770
A54: Pool | B54: =-'TB Combined'!H51 -> -3117.08
A55: Pest Control | B55: =-'TB Combined'!H52 -> -173.35
A56: Landscaping | B56: =-'TB Combined'!H53 -> -2743
A57: Legal | B57: =-'TB Combined'!H54 -> -2101.94
A58: Realtor Commissions | B58: =-'TB Combined'!H55 -> -15620
A59: Management fees | B59: =-'TB Combined'!H56 -> -1663.59
A60: Plumbing | B60: =-'TB Combined'!H57 -> -5238.07
A61: HVAC (Heat, Ventilation, Air) | B61: =-'TB Combined'!H58 -> -13299.9
A62: General Maintenance Labor | B62: =-'TB Combined'!H59 -> -965.32
... A75: Property Taxes | B75: =-'TB Combined'!H72 -> -114345.58
A76: Total Operating Expenses | B76: =SUM(B50:B75) -> -366889.71
A78: NET OPERATING INCOME | B78: =B48+B76 -> 605437.99
A80: Acquisition Fees | B80: =-'TB Combined'!H79 -> -344000
A81: Bank Fees | B81: =-'TB Combined'!H80 -> -575
A82: Due Diligence | B82: =-'TB Combined'!H81 -> -113505.01
A83: Guarantor Fee | B83: =-'TB Combined'!H82 -> -100000
A84: Management Fees | B84: =-'TB Combined'!H83 -> -70065.01
A85: Professional Fees | B85: =-'TB Combined'!H84-'TB Combined'!H78 -> -38723
A86: Remodeling Costs | B86: =-SUM('TB Combined'!H73:H77) -> 0
A87: Other Costs | B87: =-'TB Combined'!H85 -> -13210
A88: Total Other Expenses | B88: =SUM(B80:B87) -> -680078.02
A90: PROFIT BEFORE TAXES, INTEREST, AND DEPRECIATION | B90: =B78+B88 -> -74640.03
A91: Interest Income | B91: =-'TB Combined'!H86 -> 16082.44
A92: Loan Interest Expense | B92: =-'TB Combined'!H87 -> -287481.82
A93: Other Interest Expense | B93: =-'TB Combined'!H88 -> -8555.0596
A94: Amortization | B94: =-'TB Combined'!H89 -> -8410.2
A95: Depreciation | B95: =-'TB Combined'!H90 -> 0
A96: PROFIT BEFORE TAXES | B96: =SUM(B90:B95) -> -363004.67
A97: Income Taxes | B97: 0
A98: NET INCOME | B98: =SUM(B96:B97) -> -363004.67

Sheet IS (Combined)
A1: Income Statement
A2: As of: Sept 2025
A3: Accounting Basis: Accrual
A4: Level of Detail: Detail View
A5: Include Zero Balance GL Accounts: No
B7: Quarter Ended | C7: Year to Date
A8: Account Name | B8: 45930 | C8: 45930 | D8: Since Inception
A9: Operating Income & Expense
A10: Income
A11: RENTS
A12: Rent Income | B12: =C12-'IS (Combined) (Q2)'!B11 -> 447725.8 | C12: =D12 -> 895738.81 | D12: =-'TB Combined'!H25 -> 895738.81
A13: Section 8 Rent | B13: =C13-'IS (Combined) (Q2)'!B12 -> 0 | C13: =D13 -> 3933 | D13: =-'TB Combined'!H26 -> 3933
A14: Bad debt | B14: =-'TB Combined'!H45 -> -54228.32 | C14: =D14 -> -54228.32 | D14: =-'TB Combined'!H45 -> -54228.32
A15: Concessions | B15: =C15-'IS (Combined) (Q2)'!B13 -> -14175 | C15: =D15 -> -15129.85 | D15: =-'TB Combined'!H27 -> -15129.85
A16: Total RENTS | B16: =SUM(B12:B15) -> 379322.48 | C16: =D16 -> 830313.64 | D16: =SUM(D12:D15) -> 830313.64
A17: FEES | C17: =D17 -> 0
A18: NSF/Returned Payment Fees | B18: =C18-'IS (Combined) (Q2)'!B16 -> 811.49 | C18: =D18 -> 1331.24 | D18: =-'TB Combined'!H28 -> 1331.24
A19: Tenant Eviction/Legal Recovery | B19: =C19-'IS (Combined) (Q2)'!B17 -> 1345.46 | C19: =D19 -> 2780.92 | D19: =-'TB Combined'!H29 -> 2780.92
A20: Pet Rent | B20: =C20-'IS (Combined) (Q2)'!B18 -> 80.32 | C20: =D20 -> 193.72 | D20: =-'TB Combined'!H30 -> 193.72
A21: 4430: Pet Fee-Non Refundable | B21: =C21 -> 236.25 | C21: =D21 -> 236.25 | D21: =-'TB Combined'!H31 -> 236.25
A22: Application Fee Income | B22: =C22-'IS (Combined) (Q2)'!B19 -> 967.5 | C22: =D22 -> 1350 | D22: =-'TB Combined'!H32 -> 1350
A23: 4445: Administration Fee | B23: =C23 -> 300.32 | C23: =D23 -> 300.32 | D23: =-'TB Combined'!H33 -> 300.32
A24: Insurance Services | B24: =C24-'IS (Combined) (Q2)'!B20 -> 2601.38 | C24: =D24 -> 5263.24 | D24: =-'TB Combined'!H34 -> 5263.24
A25: Insurance Admin Fees | B25: =C25-'IS (Combined) (Q2)'!B21 -> 51 | C25: =D25 -> 81 | D25: =-'TB Combined'!H35 -> 81
A26: Security Deposit Insurance | B26: =C26-'IS (Combined) (Q2)'!B22 -> 3050 | C26: =D26 -> 5300 | D26: =-'TB Combined'!H36 -> 5300
A27: Break Lease | B27: =C27-'IS (Combined) (Q2)'!B23 -> 14226.25 | C27: =D27 -> 17996.8 | D27: =-'TB Combined'!H37 -> 17996.8
A28: Late Fee | B28: =C28-'IS (Combined) (Q2)'!B24 -> 5318.69 | C28: =D28 -> 9473.42 | D28: =-'TB Combined'!H38 -> 9473.42
A29: Utility Reimbursement Fee | B29: =C29-'IS (Combined) (Q2)'!B25 -> 12585.35 | C29: =D29 -> 24467.27 | D29: =-'TB Combined'!H39 -> 24467.27
A30: Garbage Fee | B30: =C30-'IS (Combined) (Q2)'!B26 -> 3602.65 | C30: =D30 -> -221 | D30: =-'TB Combined'!H40 -> -221
A31: Total FEES | B31: =SUM(B18:B30) -> 45176.66 | C31: =D31 -> 68553.18 | D31: =SUM(D18:D30) -> 68553.18
A32: Deposit Forfeit | B32: =C32-'IS (Combined) (Q2)'!B28 -> 9350 | C32: =D32 -> 16760 | D32: =-'TB Combined'!H41 -> 16760
A33: Laundry Income | B33: =C33-'IS (Combined) (Q2)'!B29 -> 577.24 | C33: =D33 -> 849.56 | D33: =-'TB Combined'!H42 -> 849.56
A34: Tenant Improvements | B34: =C34-'IS (Combined) (Q2)'!B30 -> 233.5 | C34: =D34 -> 519.75 | D34: =-'TB Combined'!H43 -> 519.75
A35: Miscellaneous Income | B35: =C35-'IS (Combined) (Q2)'!B31 -> 94.5 | C35: =D35 -> 1103.25 | D35: =-'TB Combined'!H44 -> 1103.25
A36: Total Operating Income | B36: =SUM(B31:B35)+B16 -> 434754.38 | C36: =SUM(C31:C35)+C16 -> 918099.38 | D36: =SUM(D31:D35)+D16 -> 918099.38
A37: Expense
A38: CLEANING AND MAINTENANCE
A39: 6071: Carpet Cleaning | B39: =C39 -> 95 | C39: =D39 -> 95 | D39: ='TB Combined'!H46 -> 95
A40: Supplies - Cleaning and Maitenance | B40: =C40-'IS (Combined) (Q2)'!B35 -> 0 | C40: =D40 -> 244.91 | D40: ='TB Combined'!H47 -> 244.91
A41: Cleaning and Maintenance -Other | B41: =C41-'IS (Combined) (Q2)'!B36 -> 4700.61 | C41: =D41 -> 9139.9 | D41: ='TB Combined'!H48 -> 9139.9
A42: Total CLEANING AND MAINTENANCE | B42: =SUM(B39:B41) -> 4795.61 | C42: =D42 -> 9479.81 | D42: =SUM(D39:D41) -> 9479.81
A43: Permits & Licenses | B43: =C43-'IS (Combined) (Q2)'!B38 -> 413.95 | C43: =D43 -> 1094.3 | D43: ='TB Combined'!H49 -> 1094.3
A44: CONTRACT SERVICES | C44: =D44 -> 0
A45: Elevator | B45: =C45-'IS (Combined) (Q2)'!B40 -> 3500 | C45: =D45 -> 3770 | D45: ='TB Combined'!H50 -> 3770
A46: Pool | B46: =C46-'IS (Combined) (Q2)'!B41 -> 1641.32 | C46: =D46 -> 3117.08 | D46: ='TB Combined'!H51 -> 3117.08
A47: Pest Control | B47: =C47-'IS (Combined) (Q2)'!B42 -> 152.14 | C47: =D47 -> 173.35 | D47: ='TB Combined'!H52 -> 173.35
A48: Landscaping | B48: =C48-'IS (Combined) (Q2)'!B43 -> -1610 | C48: =D48 -> 2743 | D48: ='TB Combined'!H53 -> 2743
A49: Total CONTRACT SERVICES | B49: =SUM(B45:B48) -> 3683.46 | C49: =D49 -> 9803.43 | D49: =SUM(D45:D48) -> 9803.43
A50: LEGAL AND OTHER PROFESSIONAL FEES | C50: =D50 -> 0
A51: Legal | B51: =C51-'IS (Combined) (Q2)'!B46 -> 1345.46 | C51: =D51 -> 2101.94 | D51: ='TB Combined'!H54 -> 2101.94
A52: Total LEGAL AND OTHER PROFESSIONAL FEES | B52: =SUM(B51) -> 1345.46 | C52: =D52 -> 2101.94 | D52: =SUM(D51) -> 2101.94
A53: MANAGEMENT FEES | C53: =D53 -> 0
A54: Commissions/Placement Fee's | C54: =D54 -> 0
A55: Realtor Commissions | B55: =C55-'IS (Combined) (Q2)'!B50 -> 12472.5 | C55: =D55 -> 15620 | D55: ='TB Combined'!H55 -> 15620
A56: Total Commissions/Placement Fee's | B56: =SUM(B55) -> 12472.5 | C56: =D56 -> 15620 | D56: =SUM(D55) -> 15620
A57: Management fees | B57: =C57-'IS (Combined) (Q2)'!B52 -> -15882.46 | C57: =D57 -> 1663.59 | D57: ='TB Combined'!H56 -> 1663.59
A58: Total MANAGEMENT FEES | B58: =SUM(B56:B57) -> -3409.96 | C58: =D58 -> 17283.59 | D58: =SUM(D56:D57) -> 17283.59
A59: REPAIRS | C59: =D59 -> 0
A60: Plumbing | B60: =C60-'IS (Combined) (Q2)'!B55 -> 3738.07 | C60: =D60 -> 5238.07 | D60: ='TB Combined'!H57 -> 5238.07
A61: HVAC (Heat, Ventilation, Air) | B61: =C61-'IS (Combined) (Q2)'!B56 -> 10607.94 | C61: =D61 -> 13299.9 | D61: ='TB Combined'!H58 -> 13299.9
A62: General Maintenance Labor | B62: =C62-'IS (Combined) (Q2)'!B57 -> -7169.79 | C62: =D62 -> 965.32 | D62: ='TB Combined'!H59 -> 965.32
A63: Key/Lock Replacement | B63: =C63-'IS (Combined) (Q2)'!B58 -> 12218.93 | C63: =D63 -> 12594.93 | D63: ='TB Combined'!H60 -> 12594.93
A64: Supplies - R&M | B64: =C64-'IS (Combined) (Q2)'!B59 -> -23631.45 | C64: =D64 -> 570.09 | D64: ='TB Combined'!H61 -> 570.09
A65: Supplies - HVAC | B65: =C65-'IS (Combined) (Q2)'!B60 -> 9560.32 | C65: =D65 -> 9901.65 | D65: ='TB Combined'!H62 -> 9901.65
A66: Total REPAIRS | B66: =SUM(B60:B65) -> 5324.02 | C66: =D66 -> 42569.96 | D66: =SUM(D60:D65) -> 42569.96
A67: UTILITIES | C67: =D67 -> 0
A68: Electricity | B68: =C68-'IS (Combined) (Q2)'!B63 -> 29693.16 | C68: =D68 -> 33763.16 | D68: ='TB Combined'!H63 -> 33763.16
A69: Water & Sewer | B69: =C69-'IS (Combined) (Q2)'!B64 -> 3726.39 | C69: =D69 -> 19854.65 | D69: ='TB Combined'!H64 -> 19854.65
A70: Garbage and Recycling | B70: =C70-'IS (Combined) (Q2)'!B65 -> -7351.33 | C70: =D70 -> 1656 | D70: ='TB Combined'!H65 -> 1656
A71: Total UTILITIES | B71: =SUM(B68:B70) -> 26068.22 | C71: =D71 -> 55273.81 | D71: =SUM(D68:D70) -> 55273.81
A72: GENERAL & ADMINISTRATIVE | C72: =D72 -> 0
A73: Appfolio/Software Charges | B73: =C73-'IS (Combined) (Q2)'!B68 -> -187.29 | C73: =D73 -> 604.71 | D73: ='TB Combined'!H66 -> 604.71
A74: Postage & Delivery | B74: =C74-'IS (Combined) (Q2)'!B69 -> 4024.18 | C74: =D74 -> 4268.89 | D74: ='TB Combined'!H67 -> 4268.89
A75: Misc. Expense/Other Gen & Admin Charges | B75: =C75-'IS (Combined) (Q2)'!B70 -> 0 | C75: =D75 -> 750 | D75: ='TB Combined'!H68 -> 750
A76: Tenant Security Deposit Insurance | B76: =C76-'IS (Combined) (Q2)'!B71 -> 37573.77 | C76: =D76 -> 40012.36 | D76: ='TB Combined'!H69 -> 40012.36
A77: Total GENERAL & ADMINISTRATIVE | B77: =SUM(B73:B76) -> 41410.66 | C77: =D77 -> 45635.96 | D77: =SUM(D73:D76) -> 45635.96
A78: Advertising | B78: =C78-'IS (Combined) (Q2)'!B73 -> 3908.61 | C78: =D78 -> 6526.11 | D78: ='TB Combined'!H70 -> 6526.11
A79: Insurance | B79: =C79-'IS (Combined) (Q2)'!B74 -> 32651.11 | C79: =D79 -> 62775.22 | D79: ='TB Combined'!H71 -> 62775.22
A80: Property Taxes | B80: =C80-'IS (Combined) (Q2)'!B75 -> 57172.79 | C80: =D80 -> 114345.58 | D80: ='TB Combined'!H72 -> 114345.58
A81: Total Operating Expense | B81: =B78+B77+B71+B66+B58+B52+B49+B42+B43+B79+B80 -> 173363.93 | C81: =C78+C77+C71+C66+C58+C52+C49+C42+C43+C79+C80 -> 366889.71 | D81: =D78+D77+D71+D66+D58+D52+D49+D42+D43+D79+D80 -> 366889.71
A83: NOI - Net Operating Income | B83: =B36-B81 -> 261390.45 | C83: =D83 -> 551209.67 | D83: =D36-D81 -> 551209.67
A84: Loan Interest Expense | B84: =C84-'IS (Combined) (Q2)'!B79 -> -182402.26 | C84: =D84 -> -287481.82 | D84: =-'TB Combined'!H87 -> -287481.82
A85: Net Operating Income after Debt Service | B85: =SUM(B83:B84) -> 78988.19 | C85: =D85 -> 263727.85 | D85: =SUM(D83:D84) -> 263727.85
D87: =D81/D36 -> 0.39961873

Sheet CapEx
A3: CAPITAL EXPENSES
A4: Appliances | B4: 1395
A5: Remodel-Gen. Maintenance Labor | B5: 40859.39
A6: Remodel - Supplies | B6: 17886.5
A7: Remodel-Exterior Renovations | B7: 26529.17
A8: ='Fixed Assets'!C15 -> Units 123 and 114 - remodels | B8: ='Fixed Assets'!E15 -> 55382.62
A9: Drainage/Storm water | B9: ='Fixed Assets'!E17 -> 10221.09
A10: Total | B10: =SUM(B4:B9) -> 152273.77

Sheet Fund Exp
A4: Administrative | B4: ='TB Combined'!H78 -> 4275
A5: Acquisition Fees | B5: ='TB Combined'!H79 -> 344000
A6: Bank Fees | B6: ='TB Combined'!H80 -> 575
A7: Due Diligence | B7: ='TB Combined'!H81 -> 113505.01
A8: Guarantor Fee | B8: ='TB Combined'!H82 -> 100000
A9: Management Fees | B9: ='TB Combined'!H83 -> 70065.01
A10: Professional Fees | B10: ='TB Combined'!H84 -> 34448
A11: Other Costs | B11: ='TB Combined'!H85 -> 13210
A12: Interest Income | B12: ='TB Combined'!H86 -> -16082.44
A13: Loan Interest Expense | B13: ='TB Combined'!H87 -> 287481.82
A14: Related Party Interest Expense | B14: ='TB Combined'!H88 -> 8555.0596
A15: Amortization | B15: ='TB Combined'!H89 -> 8410.2
A16: Depreciation | B16: ='TB Combined'!H90 -> 0

Sheet Fixed Assets
A3: Asset | B3: Asset Type | C3: Details | D3: Acquisition date | E3: Purchase price | F3: life
A4: Building | D4: 45755
B5: Land | C5: Purchase price allocation | D5: =D4 -> 45755 | E5: 2050000 | F5: N/A
B6: Building | C6: Purchase price allocation | D6: =D5 -> 45755 | E6: 11817000 | F6: 27.5
B7: Equipment | C7: Purchase price allocation | D7: 45755 | E7: 2575500 | F7: 5
B8: Improvements | C8: Purchase price allocation | D8: =D6 -> 45755 | E8: 757500 | F8: 15
A10: Closing Costs | B10: Land | C10: Closing Costs Allocation | D10: =D8 -> 45755 | E10: =ROUND([3]Purchase!E58,2) -> 15950.67 | F10: N/A
B11: Building | C11: Closing Costs Allocation | D11: =D10 -> 45755 | E11: =ROUND([3]Purchase!E59,2) -> 91945.86 | F11: 27.5
B12: Equipment | C12: Closing Costs Allocation | D12: 45755 | E12: =ROUND([3]Purchase!E60,2) -> 20039.48 | F12: 5
B13: Improvements | C13: Closing Costs Allocation | D13: =D11 -> 45755 | E13: =ROUND([3]Purchase!E61,2) -> 5893.97 | F13: 15
A15: Improvements | C15: Units 123 and 114 - remodels | D15: 45755 | E15: 55382.62 | F15: 15
A16: Improvements | D16: 45772 | E16: 5000 | F16: 15
A17: Improvements | C17: Drainage | D17: ='[3]Bank Movements (Sorted) (2)'!E34 -> 45814 | E17: =-'[3]Bank Movements (Sorted) (2)'!H34 -> 10221.09 | F17: 15
A18: Improvements | D18: 45859 | E18: =-'[4]Movements Sorted Q3'!H13-'[4]Movements Sorted Q3'!H14 -> 16613.41 | F18: 15
A19: Improvements | D19: 45911 | E19: =-'[4]Movements Sorted Q3'!H9-'[4]Movements Sorted Q3'!H10 -> 16004.48 | F19: 15
A20: Improvements | E20: =SUM('TB Combined'!B73:B77) -> 199699.07 | F20: 15
A33: Total | E33: =SUM(E5:E32) -> 17636751

Sheet Cash Flow (Combined)
A1: Cash Flow
A3: Account Name | B3: Fiscal Year To Date | C3: Combined
A4: Operating Income & Expense
A5: Income
A6: RENTS
A7: Rent Income | B7: 346908.26 | C7: ='IS (Combined)'!D12 -> 895738.81
A8: Section 8 Rent | B8: 3933 | C8: ='IS (Combined)'!D13 -> 3933
A9: Concessions | B9: -954.85 | C9: ='IS (Combined)'!D15 -> -15129.85
A10: Total RENTS | B10: 349886.41 | C10: ='IS (Combined)'!D16 -> 830313.64
A11: FEES | C11: ='IS (Combined)'!D17 -> 0
A12: NSF/Returned Payment Fees | B12: 519.75 | C12: ='IS (Combined)'!D18 -> 1331.24
A13: Tenant Eviction/Legal Recovery | B13: 1435.46 | C13: ='IS (Combined)'!D19 -> 2780.92
A14: Pet Rent | B14: 113.4 | C14: ='IS (Combined)'!D20 -> 193.72
A15: Application Fee Income | B15: 382.5 | C15: ='IS (Combined)'!D22 -> 1350
A16: Insurance Services | B16: 2661.86 | C16: ='IS (Combined)'!D24 -> 5263.24
A17: Insurance Admin Fees | B17: 30 | C17: ='IS (Combined)'!D25 -> 81
A18: Security Deposit Insurance | B18: 2250 | C18: ='IS (Combined)'!D26 -> 5300
A19: Break Lease | B19: 3770.55 | C19: ='IS (Combined)'!D27 -> 17996.8
A20: Late Fee | B20: 4154.73 | C20: ='IS (Combined)'!D28 -> 9473.42
A21: Utility Reimbursement Fee | B21: 11881.92 | C21: ='IS (Combined)'!D29 -> 24467.27
A22: Garbage Fee | B22: -3823.65 | C22: ='IS (Combined)'!D30 -> -221
A23: Total FEES | B23: 23376.52 | C23: ='IS (Combined)'!D31 -> 68553.18
A24: Deposit Forfeit | B24: 7410 | C24: ='IS (Combined)'!D32 -> 16760
A25: Laundry Income | B25: 272.32 | C25: ='IS (Combined)'!D33 -> 849.56
A26: Tenant Improvements | B26: 286.25 | C26: ='IS (Combined)'!D34 -> 519.75
A27: Miscellaneous Income | B27: 1008.75 | C27: ='IS (Combined)'!D35 -> 1103.25
A28: Total Operating Income | B28: 382240.25 | C28: ='IS (Combined)'!D36 -> 918099.38
A29: Expense | C29: ='IS (Combined)'!D37 -> 0
A30: CLEANING AND MAINTENANCE | C30: ='IS (Combined)'!D38 -> 0
A31: Supplies - Cleaning and Maitenance | B31: 244.91 | C31: ='IS (Combined)'!D40 -> 244.91
A32: Cleaning and Maintenance -Other | B32: 4439.29 | C32: ='IS (Combined)'!D41 -> 9139.9
A33: Total CLEANING AND MAINTENANCE | B33: 4684.2 | C33: ='IS (Combined)'!D42 -> 9479.81
A34: Permits & Licenses | B34: 680.35 | C34: ='IS (Combined)'!D43 -> 1094.3
A35: CONTRACT SERVICES | C35: ='IS (Combined)'!D44 -> 0
A36: Elevator | B36: 270 | C36: ='IS (Combined)'!D45 -> 3770
A37: Pool | B37: 1475.76 | C37: ='IS (Combined)'!D46 -> 3117.08
A38: Pest Control | B38: 21.21 | C38: ='IS (Combined)'!D47 -> 173.35
A39: Landscaping | B39: 4353 | C39: ='IS (Combined)'!D48 -> 2743
A40: Total CONTRACT SERVICES | B40: 6119.97 | C40: ='IS (Combined)'!D49 -> 9803.43
A41: LEGAL AND OTHER PROFESSIONAL FEES | C41: ='IS (Combined)'!D50 -> 0
A42: Legal | B42: 756.48 | C42: ='IS (Combined)'!D51 -> 2101.94
A43: Total LEGAL AND OTHER PROFESSIONAL FEES | B43: 756.48 | C43: ='IS (Combined)'!D52 -> 2101.94
A44: MANAGEMENT FEES | C44: ='IS (Combined)'!D53 -> 0
A45: Commissions/Placement Fee's | C45: ='IS (Combined)'!D54 -> 0
A46: Realtor Commissions | B46: 3147.5 | C46: ='IS (Combined)'!D55 -> 15620
A47: Total Commissions/Placement Fee's | B47: 3147.5 | C47: ='IS (Combined)'!D56 -> 15620
A48: Management fees | B48: 17546.05 | C48: ='IS (Combined)'!D57 -> 1663.59
A49: Total MANAGEMENT FEES | B49: 20693.55 | C49: ='IS (Combined)'!D58 -> 17283.59
A50: REPAIRS | C50: ='IS (Combined)'!D59 -> 0
A51: Plumbing | B51: 1500 | C51: ='IS (Combined)'!D60 -> 5238.07
A52: HVAC (Heat, Ventilation, Air) | B52: 2691.96 | C52: ='IS (Combined)'!D61 -> 13299.9
A53: General Maintenance Labor | B53: 8135.11 | C53: ='IS (Combined)'!D62 -> 965.32
A54: Key/Lock Replacement | B54: 376 | C54: ='IS (Combined)'!D63 -> 12594.93
A55: Supplies - R&M | B55: 24201.54 | C55: ='IS (Combined)'!D64 -> 570.09
A56: Supplies - HVAC | B56: 341.33 | C56: ='IS (Combined)'!D65 -> 9901.65
A57: Total REPAIRS | B57: 37245.94 | C57: ='IS (Combined)'!D66 -> 42569.96
A58: UTILITIES | C58: ='IS (Combined)'!D67 -> 0
A59: Electricity | B59: 4070 | C59: ='IS (Combined)'!D68 -> 33763.16
A60: Water & Sewer | B60: 16128.26 | C60: ='IS (Combined)'!D69 -> 19854.65
A61: Garbage and Recycling | B61: 9007.33 | C61: ='IS (Combined)'!D70 -> 1656
A62: Total UTILITIES | B62: 29205.59 | C62: ='IS (Combined)'!D71 -> 55273.81
A63: GENERAL & ADMINISTRATIVE | C63: ='IS (Combined)'!D72 -> 0
A64: Appfolio/Software Charges | B64: 792 | C64: ='IS (Combined)'!D73 -> 604.71
A65: Postage & Delivery | B65: 244.71 | C65: ='IS (Combined)'!D74 -> 4268.89
A66: Misc. Expense/Other Gen & Admin Charges | B66: 750 | C66: ='IS (Combined)'!D75 -> 750
A67: Tenant Security Deposit Insurance | B67: 2438.59 | C67: ='IS (Combined)'!D76 -> 40012.36
A68: Total GENERAL & ADMINISTRATIVE | B68: 4225.3 | C68: ='IS (Combined)'!D77 -> 45635.96
A69: Advertising | B69: 2617.5 | C69: ='IS (Combined)'!D78 -> 6526.11
A70: Insurance | C70: ='IS (Combined)'!D79 -> 62775.22
A71: Property Taxes | C71: ='IS (Combined)'!D80 -> 114345.58
A72: Total Operating Expense | B72: 106228.88 | C72: ='IS (Combined)'!D81 -> 366889.71
A74: NOI - Net Operating Income | B74: 276011.37 | C74: ='IS (Combined)'!D83 -> 551209.67
A76: Other Income & Expense
A77: Other Expense
A78: CAPITAL EXPENSES
A79: Appliances | B79: 1395 | C79: ='IS (Combined)'!#REF! -> #REF!
A80: Remodel-Gen. Maintenance Labor | B80: 40859.39 | C80: ='IS (Combined)'!#REF! -> #REF!
A81: Remodel - Supplies | B81: 17886.5 | C81: ='IS (Combined)'!#REF! -> #REF!
A82: Remodel-Exterior Renovations | B82: 26529.17 | C82: ='IS (Combined)'!#REF! -> #REF!
A83: Administrative | B83: 750 | C83: ='IS (Combined)'!#REF! -> #REF!
A84: Acquisition Fees | C84: ='IS (Combined)'!#REF! -> #REF!
A85: Bank Fees | C85: ='IS (Combined)'!#REF! -> #REF!
A86: Due Diligence | C86: ='IS (Combined)'!#REF! -> #REF!
A87: Guarantor Fee | C87: ='IS (Combined)'!#REF! -> #REF!
A88: Management Fees | C88: ='IS (Combined)'!#REF! -> #REF!
A89: Professional Fees | C89: ='IS (Combined)'!#REF! -> #REF!
A90: Other Costs | C90: ='IS (Combined)'!#REF! -> #REF!
A91: Interest Income | C91: ='IS (Combined)'!#REF! -> #REF!
A92: Interest Expense | C92: ='IS (Combined)'!#REF! -> #REF!
C93: ='IS (Combined)'!#REF! -> #REF!
A94: Amortization | C94: ='IS (Combined)'!#REF! -> #REF!
A95: Depreciation | C95: ='IS (Combined)'!#REF! -> #REF!
C96: ='IS (Combined)'!#REF! -> #REF!
A97: Total CAPITAL EXPENSES | B97: 87420.06 | C97: =SUM(C79:C96) -> #REF!
A98: Total Other Expense | B98: 87420.06 | C98: =C97 -> #REF!
A100: Net Other Income | B100: -87420.06 | C100: =-C98 -> #REF!
C101: ='IS (Combined)'!#REF! -> #REF!
A102: Total Income | B102: 382240.25 | C102: ='IS (Combined)'!#REF! -> #REF!
A103: Total Expense | B103: 193648.94 | C103: =C98+C72 -> #REF!
A105: Net Income | B105: 188591.31 | C105: =C102-C103 -> #REF!
...

Sheet TB Combined
A1: Combined Trial Balance
A2: At 9-30-2025
A4: Account Name | B4: Year to Month End | D4: Top | F4: Eliminations | H4: Combined
A5: Operating Account | B5: 17506.83 | D5: ='Balance Sheet & IS'!B7 -> 1072818 | H5: =SUM(B5:G5) -> 1090324.8
A6: Security Account | B6: 88145 | H6: =SUM(B6:G6) -> 88145
A7: Accounts Receivable | B7: 103505.18 | D7: ='Balance Sheet & IS'!B8 -> 101712.79 | F7: =-D7-F45 -> -155941.11 | H7: =SUM(B7:G7) -> 49276.86
A8: Mgmt Held Security Deposits | B8: -92730 | H8: =SUM(B8:G8) -> -92730
A9: Prepaid Rent | B9: -18170.39 | H9: =SUM(B9:G9) -> -18170.39
A10: Prepaid Insurance | D10: ='Balance Sheet & IS'!B9 -> 60248.17 | H10: =SUM(B10:G10) -> 60248.17
A11: Prepaid Interest | D11: ='Balance Sheet & IS'!B10 -> 0 | H11: =SUM(B11:G11) -> 0
A12: Prepaid Other | D12: ='Balance Sheet & IS'!B11 -> 0 | H12: =SUM(B12:G12) -> 0
A13: Fixed Assets, Net | D13: ='Balance Sheet & IS'!B12 -> 17423169 | F13: =5000-SUM(F73:F77) -> 204699.07 | H13: =SUM(B13:G13) -> 17627868
A14: Capitalized Loan Costs, Net | D14: ='Balance Sheet & IS'!B13 -> 168204.2 | H14: =SUM(B14:G14) -> 168204.2
A15: Deposits in Escrow | D15: ='Balance Sheet & IS'!B14 -> 99209.46 | H15: =SUM(B15:G15) -> 99209.46
A16: Property Tax in Escrow | D16: ='Balance Sheet & IS'!B15 -> 215081.24 | H16: =SUM(B16:G16) -> 215081.24
A17: Other Assets | D17: ='Balance Sheet & IS'!B16 -> 0 | H17: =SUM(B17:G17) -> 0
A18: Accounts Payable | B18: -12124.33 | H18: =SUM(B18:G18) -> -12124.33
A19: Accounts Payable-Top | D19: =-'Balance Sheet & IS'!B21 -> -8655.1596 | H19: =SUM(B19:G19) -> -8655.1596
A20: Property Taxes Payable | D20: =-'Balance Sheet & IS'!B22 -> -177461.29 | H20: =SUM(B20:G20) -> -177461.29
A21: Management Fee Payable | D21: =-'Balance Sheet & IS'!B23 -> -36450 | H21: =SUM(B21:G21) -> -36450
A22: Notes Payable | D22: =-'Balance Sheet & IS'!B24 -> -12180000 | H22: =SUM(B22:G22) -> -12180000
A23: Owner Contribution | B23: -101712.79 | D23: =-'Balance Sheet & IS'!B28 -> -7290000 | F23: =-B23 -> 101712.79 | H23: =SUM(B23:G23) -> -7290000
A24: Owner Distribution | B24: 493060.47 | D24: =-'Balance Sheet & IS'!B47 -> -485533.47 | F24: =-F78-2527-5000 -> -7527 | H24: =SUM(B24:G24) -> 0
A25: Rent Income | B25: -794634.06 | D25: =-'Balance Sheet & IS'!B46 -> -101104.75 | H25: =SUM(B25:G25) -> -895738.81
A26: Section 8 Rent | B26: -3933 | H26: =SUM(B26:G26) -> -3933
A27: Concessions | B27: 15129.85 | H27: =SUM(B27:G27) -> 15129.85
A28: NSF/Returned Payment Fees | B28: -1331.24 | H28: =SUM(B28:G28) -> -1331.24
A29: Tenant Eviction/Legal Recovery | B29: -2780.92 | H29: =SUM(B29:G29) -> -2780.92
A30: Pet Rent | B30: -193.72 | H30: =SUM(B30:G30) -> -193.72
A31: 4430: Pet Fee-Non Refundable | B31: -236.25 | H31: =SUM(B31:G31) -> -236.25
A32: Application Fee Income | B32: -1350 | H32: =SUM(B32:G32) -> -1350
A33: 4445: Administration Fee | B33: -300.32 | H33: =SUM(B33:G33) -> -300.32
A34: Insurance Services | B34: -5263.24 | H34: =SUM(B34:G34) -> -5263.24
A35: Insurance Admin Fees | B35: -81 | H35: =SUM(B35:G35) -> -81
A36: Security Deposit Insurance | B36: -5300 | H36: =SUM(B36:G36) -> -5300
A37: Break Lease | B37: -17996.8 | H37: =SUM(B37:G37) -> -17996.8
... A44: Miscellaneous Income | B44: -1103.25 | H44: =SUM(B44:G44) -> -1103.25
A45: Bad Debt | F45: ='Bad Debt'!H19 -> 54228.32 | H45: =SUM(B45:G45) -> 54228.32
A46: 6071: Carpet Cleaning | B46: 95 | H46: =SUM(B46:G46) -> 95
A47: Supplies - Cleaning and Maitenance | B47: 244.91 | H47: =SUM(B47:G47) -> 244.91
A48: Cleaning and Maintenance -Other | B48: 9139.9 | H48: =SUM(B48:G48) -> 9139.9
A49: Permits & Licenses | B49: 1094.3 | H49: =SUM(B49:G49) -> 1094.3
A50: Elevator | B50: 3770 | H50: =SUM(B50:G50) -> 3770
A51: Pool | B51: 3117.08 | H51: =SUM(B51:G51) -> 3117.08
A52: Pest Control | B52: 173.35 | H52: =SUM(B52:G52) -> 173.35
A53: Landscaping | B53: 2743 | H53: =SUM(B53:G53) -> 2743
A54: Legal | B54: 2101.94 | H54: =SUM(B54:G54) -> 2101.94
A55: Realtor Commissions | B55: 15620 | H55: =SUM(B55:G55) -> 15620
A56: Management fees | B56: 1663.59 | H56: =SUM(B56:G56) -> 1663.59
A57: Plumbing | B57: 5238.07 | H57: =SUM(B57:G57) -> 5238.07
... A70: Advertising | B70: 6526.11 | H70: =SUM(B70:G70) -> 6526.11
A71: Insurance | D71: =-'Balance Sheet & IS'!B54 -> 60248.22 | F71: 2527 | H71: =SUM(B71:G71) -> 62775.22
A72: Property Taxes | D72: =-'Balance Sheet & IS'!B57 -> 114345.58 | H72: =SUM(B72:G72) -> 114345.58
A73: Appliances | B73: 2694 | F73: =-B73 -> -2694 | H73: =SUM(B73:G73) -> 0
A74: Remodel-Gen. Maintenance Labor | B74: 65371.93 | F74: =-B74 -> -65371.93 | H74: =SUM(B74:G74) -> 0
A75: Remodel - Supplies | B75: 45986.4 | F75: =-B75 -> -45986.4 | H75: =SUM(B75:G75) -> 0
A76: Remodel-Exterior Renovations | B76: 67344.11 | F76: =-B76 -> -67344.11 | H76: =SUM(B76:G76) -> 0
A77: 7060: Landscaping | B77: 18302.63 | F77: =-B77 -> -18302.63 | H77: =SUM(B77:G77) -> 0
A78: Administrative | B78: 4275 | H78: =SUM(B78:G78) -> 4275
A79: Acquisition Fees | D79: =-'Balance Sheet & IS'!B50 -> 344000 | H79: =SUM(B79:G79) -> 344000
A80: Bank Fees | D80: =-'Balance Sheet & IS'!B51 -> 575 | H80: =SUM(B80:G80) -> 575
A81: Due Diligence | D81: =-'Balance Sheet & IS'!B52 -> 113505.01 | H81: =SUM(B81:G81) -> 113505.01
A82: Guarantor Fee | D82: =-'Balance Sheet & IS'!B53 -> 100000 | H82: =SUM(B82:G82) -> 100000
A83: Management Fees | D83: =-'Balance Sheet & IS'!B55 -> 70065.01 | H83: =SUM(B83:G83) -> 70065.01
A84: Professional Fees | D84: =-'Balance Sheet & IS'!B56 -> 34448 | H84: =SUM(B84:G84) -> 34448
A85: Other Costs | D85: =-'Balance Sheet & IS'!B58 -> 13210 | H85: =SUM(B85:G85) -> 13210
A86: Interest Income | D86: =-'Balance Sheet & IS'!B63 -> -16082.44 | H86: =SUM(B86:G86) -> -16082.44
A87: Loan Interest Expense | D87: =-'Balance Sheet & IS'!B64 -> 287481.82 | H87: =SUM(B87:G87) -> 287481.82
A88: Related Party Interest Expense | D88: =-'Balance Sheet & IS'!B65 -> 8555.0596 | H88: =SUM(B88:G88) -> 8555.0596
A89: Amortization | D89: =-'Balance Sheet & IS'!B66 -> 8410.2 | H89: =SUM(B89:G89) -> 8410.2
A90: Depreciation | H90: =SUM(B90:G90) -> 0
B92: =SUM(B5:B91) -> 4.0017767e-11 | D92: =SUM(D5:D91) -> 0.0099999989 | F92: =SUM(F5:F91) -> 0 | H92: =SUM(H5:H91) -> 0.0099999989

Sheet IS
A1: Income Statement
A2: Exported On: 11/05/2025 09:20 PM
A4: Cruise Property Management
A5: Properties: Active
A6: As of: Sep 2025
A7: Accounting Basis: Accrual
A8: Level of Detail: Detail View
A9: Include Zero Balance GL Accounts: No
A11: Account Name | B11: Selected Month | C11: % of Selected Month | D11: Year to Month End | E11: % of Year to Month End
A12: Operating Income & Expense
A13: Income
A14: RENTS
A15: Rent Income | B15: 149866 | C15: 90.41 | D15: 794634.06 | E15: 91.21
A16: Section 8 Rent | B16: 0 | C16: 0 | D16: 3933 | E16: 0.45
A17: Concessions | B17: -4390 | C17: -2.65 | D17: -15129.85 | E17: -1.74
A18: Total RENTS | B18: 145476 | C18: 87.77 | D18: 783437.21 | E18: 89.92
A19: FEES
A20: NSF/Returned Payment Fees | B20: 282.12 | C20: 0.17 | D20: 1331.24 | E20: 0.15
A21: Tenant Eviction/Legal Recovery | B21: 0 | C21: 0 | D21: 2780.92 | E21: 0.32
A22: Pet Rent | B22: 42.52 | C22: 0.03 | D22: 193.72 | E22: 0.02
A23: Pet Fee-Non Refundable | B23: 236.25 | C23: 0.14 | D23: 236.25 | E23: 0.03
A24: Application Fee Income | B24: 292.5 | C24: 0.18 | D24: 1350 | E24: 0.15
A25: Administration Fee | B25: 25 | C25: 0.02 | D25: 300.32 | E25: 0.03
A26: Insurance Services | B26: 773.83 | C26: 0.47 | D26: 5263.24 | E26: 0.6
A27: Insurance Admin Fees | B27: 12.83 | C27: 0.01 | D27: 81 | E27: 0.01
A28: Security Deposit Insurance | B28: 900 | C28: 0.54 | D28: 5300 | E28: 0.61
A29: Break Lease | B29: 4315.5 | C29: 2.6 | D29: 17996.8 | E29: 2.07
A30: Late Fee | B30: 1235.54 | C30: 0.75 | D30: 9473.42 | E30: 1.09
A31: Utility Reimbursement Fee | B31: 4187.85 | C31: 2.53 | D31: 24467.27 | E31: 2.81
... A38: Total Operating Income | B38: 165754.27 | C38: 100 | D38: 871222.95 | E38: 100
A39: Expense
A40: CLEANING AND MAINTENANCE
A41: Carpet Cleaning | B41: 95 | C41: 0.06 | D41: 95 | E41: 0.01
A42: Supplies - Cleaning and Maitenance | B42: 0 | C42: 0 | D42: 244.91 | E42: 0.03
A43: Cleaning and Maintenance -Other | B43: 1638.7 | C43: 0.99 | D43: 9139.9 | E43: 1.05
A44: Total CLEANING AND MAINTENANCE | B44: 1733.7 | C44: 1.05 | D44: 9479.81 | E44: 1.09
A45: Permits & Licenses | B45: 51.5 | C45: 0.03 | D45: 1094.3 | E45: 0.13
A46: CONTRACT SERVICES
A47: Elevator | B47: 3500 | C47: 2.11 | D47: 3770 | E47: 0.43
A48: Pool | B48: 531.4 | C48: 0.32 | D48: 3117.08 | E48: 0.36
A49: Pest Control | B49: 152.14 | C49: 0.09 | D49: 173.35 | E49: 0.02
A50: Landscaping | B50: 600 | C50: 0.36 | D50: 2743 | E50: 0.31
A51: Total CONTRACT SERVICES | B51: 4783.54 | C51: 2.89 | D51: 9803.43 | E51: 1.13
A52: LEGAL AND OTHER PROFESSIONAL FEES
A53: Legal | B53: 0 | C53: 0 | D53: 2101.94 | E53: 0.24
A54: Total LEGAL AND OTHER PROFESSIONAL FEES | B54: 0 | C54: 0 | D54: 2101.94 | E54: 0.24
A55: MANAGEMENT FEES
A56: Commissions/Placement Fee's
A57: Realtor Commissions | B57: 5597.5 | C57: 3.38 | D57: 15620 | E57: 1.79
A58: Total Commissions/Placement Fee's | B58: 5597.5 | C58: 3.38 | D58: 15620 | E58: 1.79
A59: Management fees | B59: 7784.77 | C59: 4.7 | D59: 40012.36 | E59: 4.59
A60: Total MANAGEMENT FEES | B60: 13382.27 | C60: 8.07 | D60: 55632.36 | E60: 6.39
A61: REPAIRS
A62: Plumbing | B62: 0 | C62: 0 | D62: 1663.59 | E62: 0.19
A63: HVAC (Heat, Ventilation, Air) | B63: 671.4 | C63: 0.41 | D63: 5238.07 | E63: 0.6
A64: General Maintenance Labor | B64: 1639.31 | C64: 0.99 | D64: 13299.9 | E64: 1.53
A65: Key/Lock Replacement | B65: 147.33 | C65: 0.09 | D65: 965.32 | E65: 0.11
A66: Supplies - R&M | B66: 510.73 | C66: 0.31 | D66: 12594.93 | E66: 1.45
A67: Supplies - HVAC | B67: 59.91 | C67: 0.04 | D67: 570.09 | E67: 0.07
A68: Total REPAIRS | B68: 3028.68 | C68: 1.83 | D68: 34331.9 | E68: 3.94
A69: UTILITIES
A70: Electricity | B70: 1771.74 | C70: 1.07 | D70: 9901.65 | E70: 1.14
A71: Water & Sewer | B71: 5900.99 | C71: 3.56 | D71: 33763.16 | E71: 3.88
A72: Garbage and Recycling | B72: 3244.18 | C72: 1.96 | D72: 19854.65 | E72: 2.28
A73: Total UTILITIES | B73: 10916.91 | C73: 6.59 | D73: 63519.46 | E73: 7.29
A74: GENERAL & ADMINISTRATIVE
A75: Appfolio/Software Charges | B75: 290 | C75: 0.17 | D75: 1656 | E75: 0.19
A76: Postage & Delivery | B76: 75 | C76: 0.05 | D76: 604.71 | E76: 0.07
A77: Misc. Expense/Other Gen & Admin Charges | B77: 0 | C77: 0 | D77: 750 | E77: 0.09
A78: Tenant Security Deposit Insurance | B78: 502.58 | C78: 0.3 | D78: 4268.89 | E78: 0.49
A79: Total GENERAL & ADMINISTRATIVE | B79: 867.58 | C79: 0.52 | D79: 7279.6 | E79: 0.84
A80: Advertising | B80: 1459 | C80: 0.88 | D80: 6526.11 | E80: 0.75
A81: Total Operating Expense | B81: 36223.18 | C81: 21.85 | D81: 189768.91 | E81: 21.78
A83: NOI - Net Operating Income | B83: 129531.09 | C83: 78.15 | D83: 681454.04 | E83: 78.22
A85: Other Income & Expense
A86: Other Expense
A87: CAPITAL EXPENSES
A88: Appliances | B88: 606.4 | C88: 0.37 | D88: 2694 | E88: 0.31
A89: Remodel-Gen. Maintenance Labor | B89: 8379.31 | C89: 5.06 | D89: 65371.93 | E89: 7.5
A90: Remodel - Supplies | B90: 1689.7 | C90: 1.02 | D90: 45986.4 | E90: 5.28
A91: Remodel-Exterior Renovations | B91: 1787.55 | C91: 1.08 | D91: 67344.11 | E91: 7.73
A92: Landscaping | B92: 0 | C92: 0 | D92: 18302.63 | E92: 2.1
A93: Administrative | B93: 3525 | C93: 2.13 | D93: 4275 | E93: 0.49
A94: Total CAPITAL EXPENSES | B94: 15987.96 | C94: 9.65 | D94: 203974.07 | E94: 23.41
A95: Total Other Expense | B95: 15987.96 | C95: 9.65 | D95: 203974.07 | E95: 23.41
A97: Net Other Income | B97: -15987.96 | C97: -9.65 | D97: -203974.07 | E97: -23.41
A99: Total Income | B99: 165754.27 | C99: 100 | D99: 871222.95 | E99: 100
A100: Total Expense | B100: 52211.14 | C100: 31.5 | D100: 393742.98 | E100: 45.19
A102: Net Income | B102: 113543.13 | C102: 68.5 | D102: 477479.97 | E102: 54.81

Sheet BS
A1: Balance Sheet
A2: Exported On: 10/14/2025 07:25 PM
A4: Properties: Active
A5: As of: 09/30/2025
A6: Accounting Basis: Accrual
A7: Level of Detail: Detail View
A8: Include Zero Balance GL Accounts: No
A10: Account Number | B10: Account Name | C10: Balance
B11: ASSETS
B12: Cash
A13: 1101 | B13: Operating Account | C13: 17506.83
A14: 1102 | B14: Security Account | C14: 88145
B15: Total Cash | C15: 105651.83
A16: 1300 | B16: Accounts Receivable | C16: 103505.18
B17: TOTAL ASSETS | C17: 209157.01
B20: LIABILITIES & CAPITAL
B21: Liabilities
B22: SECURITY DEPOSITS
A23: 2101 | B23: Mgmt Held Security Deposits | C23: 92730
B24: Total SECURITY DEPOSITS | C24: 92730
A25: 2300 | B25: Prepaid Rent | C25: 18170.39
A26: 2500 | B26: Accounts Payable | C26: 12094.77
B27: Total Liabilities | C27: 122995.16
B28: Capital
A29: 3150 | B29: Owner Contribution | C29: 101712.79
A30: 3250 | B30: Owner Distribution | C30: -418060.47
B31: Calculated Retained Earnings | C31: 402509.53
B32: Total Capital | C32: 86161.85
B33: TOTAL LIABILITIES & CAPITAL | C33: 209157.01

Sheet Bad Debt
A1: Unit | B1: Name | C1: Tenant Status | D1: Tags | E1: Phone Numbers | F1: Move In | G1: Move Out | H1: Amount Receivable | I1: Delinquent Subsidy Amount | J1: 0-30 | K1: 30+
A3: -> Allaire on 41st St - 5525 SW 41 St Pembroke Park, FL 33023
A4: 109 | B4: Joseph, Mannes | C4: Past | E4: Mobile: (786) 991-5452 | F4: 45717 | G4: 45838 | H4: 475 | I4: 0 | J4: 0 | K4: 475
A5: 118 | B5: Mitchell , Annmarie Marcia | C5: Past | E5: Home: (954) 901-6814 | F5: 45717 | G5: 45890 | H5: 10593.98 | I5: 0 | J5: 0 | K5: 10593.98
A6: 121 | B6: Zephir, Walando | C6: Past | E6: Phone: (754) 207-9389 | F6: 45717 | G6: 45838 | H6: 4300 | I6: 0 | J6: 0 | K6: 4300
A7: 122 | B7: Simms, Elizabeth | C7: Past | E7: Home: (754) 204-4281 | F7: 45717 | G7: 45900 | H7: 2687 | I7: 0 | J7: 2687 | K7: 0
A8: 124 | B8: Schieck, Todd | C8: Past | E8: Phone: (303) 993-9414 | F8: 45717 | G8: 45866 | H8: 175 | I8: 0 | J8: 0 | K8: 175
A9: 207 | B9: Brown, Tracy | C9: Past | E9: Home: (954) 391-0478 | F9: 45717 | G9: 45808 | H9: 780 | I9: 0 | J9: 0 | K9: 780
A10: 209 | B10: Pouncy, Shawn | C10: Past | D10: LeaseLock | F10: 45717 | G10: 45758 | H10: 12695.36 | I10: 0 | J10: 0 | K10: 12695.36
A11: 219 | B11: Hyacinthe, Albertha | C11: Past | E11: Home: (954) 483-5709 | F11: 45717 | G11: 45807 | H11: 940 | I11: 0 | J11: 0 | K11: 940
A12: 224 | B12: St-Armond, Geminiaya | C12: Past | E12: Phone: (786) 436-6053 | F12: 45717 | G12: 45885 | H12: 4269.5 | I12: 0 | J12: 0 | K12: 4269.5
A13: 305 | B13: Othelot, Aaliyah | C13: Past | E13: Home: (305) 509-9578 | F13: 45717 | G13: 45904 | H13: 165 | I13: 0 | J13: 165 | K13: 0
A14: 306 | B14: Allen , Karrington | C14: Past | F14: 45717 | G14: 45826 | H14: 13642.48 | I14: 0 | J14: 0 | K14: 13642.48
A15: 323 | B15: Boyd, Samantha | C15: Past | E15: Home: (813) 822-1101 | F15: 45717 | G15: 45899 | H15: 1085 | I15: 0 | J15: 465 | K15: 620
A16: 426 | B16: Pinet, Wilene | C16: Past | E16: Home: (305) 305-1241 | F16: 45717 | G16: 45757 | H16: 2420 | I16: 0 | J16: 0 | K16: 2420
H17: 54228.32 | I17: 0 | J17: 3317 | K17: 50911.32
A19: Total | H19: 54228.32 | I19: 0 | J19: 3317 | K19: 50911.32
H21: =H16+H14+H11+H10+H9+H8+H6+H4 -> 35427.84
H22: =H15+H12+H7+H5 -> 18635.48
H23: =H13 -> 165

Sheet Balance Sheet & IS
A1: Allaire on 41st top level
A2: Unaudited Consolidated Balance Sheet
A3: As of 9/30/2025
A6: ASSETS
A7: Cash and Cash Equivalents | B7: 1072818
A8: Accounts Receivable Intercompany | B8: 101712.79
A9: Prepaid Insurance | B9: 60248.17
A10: Prepaid Interest
A11: Prepaid Other
A12: Fixed Assets, Net | B12: 17423169
A13: Capitalized Loan Costs, Net | B13: 168204.2
A14: Deposits in Escrow | B14: 99209.46
A15: Property Tax in Escrow | B15: 215081.24
A16: Other Assets
A17: TOTAL ASSETS | B17: 19140443
A19: LIABILITIES AND EQUITY
A20: Liabilities
A21: Accounts Payable | B21: 8655.1596
A22: Property Taxes Payable | B22: 177461.29
A23: Management Fee Payable | B23: 36450
A24: Notes Payable | B24: 12180000
A25: Other Liabilities
A26: Total Liabilities | B26: 12402566
A27: Equity
A28: Members Equity | B28: 7290000
A29: Current Year Net Income | B29: -552123.24
A30: Accumulated Earnings & Profits
A31: Total Equity | B31: 6737876.8
A32: TOTAL LIABILITIES AND EQUITY | B32: 19140443
B34: -0.0099999979
A40: Allaire on 41st top level
A41: Unaudited Consolidated Income Statement
A42: January 1, 2025 through September 30, 2025
A45: REVENUES
A46: Rent Income | B46: 101104.75
A47: Distribution Income | B47: 485533.47
A48: Gross Profit | B48: 586638.22
A50: Acquisition Fees | B50: -344000
A51: Bank Fees | B51: -575
A52: Due Diligence | B52: -113505.01
A53: Guarantor Fee | B53: -100000
A54: Insurance | B54: -60248.22
A55: Management Fees | B55: -70065.01
A56: Professional Fees | B56: -34448
A57: Property Taxes | B57: -114345.58
A58: Other Costs | B58: -13210
A59: Total expenses
A61: Other Income/(Expense)
A62: PROFIT BEFORE TAXES, INTEREST, AND DEPRECIATION | B62: -263758.6
A63: Interest Income | B63: 16082.44
A64: Loan Interest Expense | B64: -287481.82
A65: Other Interest Expense | B65: -8555.0596
A66: Amortization | B66: -8410.2
A67: Depreciation
A68: PROFIT BEFORE TAXES | B68: -552123.24
A69: Income Taxes
A70: NET INCOME | B70: -552123.24

Sheet Debt Service
A1: CITADEL ALLAIRE ON 41ST LLC
A2: Opening Balance | B2: 12180000
A3: Current Interest Rate | B3: 0.0586
A5: Monthly Interest | B5: 61461.63
A6: Tax Escrow | B6: 19552.84 | C6: =B6*12 -> 234634.08
A7: Insurance Escrow | B7: 10443.02
A8: Replacement Reserve Escrow | B8: 1708.33
A9: Total Payment | B9: =SUM(B5:B8) -> 93165.82

Sheet IS (Combined) (Q2)
A1: Income Statement
A2: As of: Jun 2025
A3: Accounting Basis: Accrual
A4: Level of Detail: Detail View
A5: Include Zero Balance GL Accounts: No
A7: Account Name | B7: Year to Month End
A8: Operating Income & Expense
A9: Income
A10: RENTS
A11: Rent Income | B11: =-'[5]TB Combined'!H25 -> 448013.01
A12: Section 8 Rent | B12: =-'[5]TB Combined'!H26 -> 3933
A13: Concessions | B13: =-'[5]TB Combined'!H27 -> -954.85
A14: Total RENTS | B14: =SUM(B11:B13) -> 450991.16
A15: FEES
A16: NSF/Returned Payment Fees | B16: =-'[5]TB Combined'!H28 -> 519.75
A17: Tenant Eviction/Legal Recovery | B17: =-'[5]TB Combined'!H29 -> 1435.46
A18: Pet Rent | B18: =-'[5]TB Combined'!H30 -> 113.4
A19: Application Fee Income | B19: =-'[5]TB Combined'!H31 -> 382.5
A20: Insurance Services | B20: =-'[5]TB Combined'!H32 -> 2661.86
A21: Insurance Admin Fees | B21: =-'[5]TB Combined'!H33 -> 30
A22: Security Deposit Insurance | B22: =-'[5]TB Combined'!H34 -> 2250
A23: Break Lease | B23: =-'[5]TB Combined'!H35 -> 3770.55
A24: Late Fee | B24: =-'[5]TB Combined'!H36 -> 4154.73
A25: Utility Reimbursement Fee | B25: =-'[5]TB Combined'!H37 -> 11881.92
A26: Garbage Fee | B26: =-'[5]TB Combined'!H38 -> -3823.65
A27: Total FEES | B27: =SUM(B16:B26) -> 23376.52
A28: Deposit Forfeit | B28: =-'[5]TB Combined'!H39 -> 7410
A29: Laundry Income | B29: =-'[5]TB Combined'!H40 -> 272.32
A30: Tenant Improvements | B30: =-'[5]TB Combined'!H41 -> 286.25
A31: Miscellaneous Income | B31: =-'[5]TB Combined'!H42 -> 1008.75
A32: Total Operating Income | B32: =SUM(B27:B31)+B14 -> 483345
A33: Expense
A34: CLEANING AND MAINTENANCE
A35: Supplies - Cleaning and Maitenance | B35: ='[5]TB Combined'!H43 -> 244.91
A36: Cleaning and Maintenance -Other | B36: ='[5]TB Combined'!H44 -> 4439.29
A37: Total CLEANING AND MAINTENANCE | B37: =SUM(B35:B36) -> 4684.2
A38: Permits & Licenses | B38: ='[5]TB Combined'!H45 -> 680.35
A39: CONTRACT SERVICES
A40: Elevator | B40: ='[5]TB Combined'!H46 -> 270
A41: Pool | B41: ='[5]TB Combined'!H47 -> 1475.76
A42: Pest Control | B42: ='[5]TB Combined'!H48 -> 21.21
A43: Landscaping | B43: ='[5]TB Combined'!H49 -> 4353
A44: Total CONTRACT SERVICES | B44: =SUM(B40:B43) -> 6119.97
A45: LEGAL AND OTHER PROFESSIONAL FEES
A46: Legal | B46: ='[5]TB Combined'!H50 -> 756.48
A47: Total LEGAL AND OTHER PROFESSIONAL FEES | B47: =SUM(B46) -> 756.48
A48: MANAGEMENT FEES
A49: Commissions/Placement Fee's
A50: Realtor Commissions | B50: ='[5]TB Combined'!H51 -> 3147.5
A51: Total Commissions/Placement Fee's | B51: =SUM(B50) -> 3147.5
A52: Management fees | B52: ='[5]TB Combined'!H52 -> 17546.05
A53: Total MANAGEMENT FEES | B53: =SUM(B51:B52) -> 20693.55
A54: REPAIRS
A55: Plumbing | B55: ='[5]TB Combined'!H53 -> 1500
A56: HVAC (Heat, Ventilation, Air) | B56: ='[5]TB Combined'!H54 -> 2691.96
A57: General Maintenance Labor | B57: ='[5]TB Combined'!H55 -> 8135.11
A58: Key/Lock Replacement | B58: ='[5]TB Combined'!H56 -> 376
A59: Supplies - R&M | B59: ='[5]TB Combined'!H57 -> 24201.54
A60: Supplies - HVAC | B60: ='[5]TB Combined'!H58 -> 341.33
A61: Total REPAIRS | B61: =SUM(B55:B60) -> 37245.94
A62: UTILITIES
A63: Electricity | B63: ='[5]TB Combined'!H59 -> 4070
A64: Water & Sewer | B64: ='[5]TB Combined'!H60 -> 16128.26
A65: Garbage and Recycling | B65: ='[5]TB Combined'!H61 -> 9007.33
A66: Total UTILITIES | B66: =SUM(B63:B65) -> 29205.59
A67: GENERAL & ADMINISTRATIVE
A68: Appfolio/Software Charges | B68: ='[5]TB Combined'!H62 -> 792
A69: Postage & Delivery | B69: ='[5]TB Combined'!H63 -> 244.71
A70: Misc. Expense/Other Gen & Admin Charges | B70: ='[5]TB Combined'!H64 -> 750
A71: Tenant Security Deposit Insurance | B71: ='[5]TB Combined'!H65 -> 2438.59
A72: Total GENERAL & ADMINISTRATIVE | B72: =SUM(B68:B71) -> 4225.3
A73: Advertising | B73: ='[5]TB Combined'!H66 -> 2617.5
A74: Insurance | B74: ='[5]TB Combined'!H67 -> 30124.11
A75: Property Taxes | B75: ='[5]TB Combined'!H68 -> 57172.79
A76: Total Operating Expense | B76: =B73+B72+B66+B61+B53+B47+B44+B37+B38+B74+B75 -> 193525.78
A78: NOI - Net Operating Income | B78: =B32-B76 -> 289819.22
A79: Loan Interest Expense | B79: =-'[5]TB Combined'!H82 -> -105079.56
A80: Net Operating Income after Debt Service | B80: =SUM(B78:B79) -> 184739.66

Sheet Cash Flow
A1: Cash Flow
A2: Exported On: 07/27/2025 02:06 PM
A4: Cruise Property Management
A5: Properties: Active
A6: Date Range: 04/01/2025 to 06/30/2025 (Last Quarter)
A7: Accounting Basis: Accrual
A8: Additional Cash GL Accounts: 1102: Security Account, 1137: Due From/To, and 1150: Exchange/Transfer
A9: Level of Detail: Detail View
A10: Include Zero Balance GL Accounts: No
A12: Account Name | B12: Selected Period | C12: % of Selected Period | D12: Fiscal Year To Date | E12: % of Fiscal Year To Date
A13: Operating Income & Expense
A14: Income
A15: RENTS
A16: Rent Income | B16: 346908.26 | C16: 90.76 | D16: 346908.26 | E16: 90.76
A17: Section 8 Rent | B17: 3933 | C17: 1.03 | D17: 3933 | E17: 1.03
A18: Concessions | B18: -954.85 | C18: -0.25 | D18: -954.85 | E18: -0.25
A19: Total RENTS | B19: 349886.41 | C19: 91.54 | D19: 349886.41 | E19: 91.54
A20: FEES
A21: NSF/Returned Payment Fees | B21: 519.75 | C21: 0.14 | D21: 519.75 | E21: 0.14
A22: Tenant Eviction/Legal Recovery | B22: 1435.46 | C22: 0.38 | D22: 1435.46 | E22: 0.38
A23: Pet Rent | B23: 113.4 | C23: 0.03 | D23: 113.4 | E23: 0.03
A24: Application Fee Income | B24: 382.5 | C24: 0.1 | D24: 382.5 | E24: 0.1
A25: Insurance Services | B25: 2661.86 | C25: 0.7 | D25: 2661.86 | E25: 0.7
A26: Insurance Admin Fees | B26: 30 | C26: 0.01 | D26: 30 | E26: 0.01
A27: Security Deposit Insurance | B27: 2250 | C27: 0.59 | D27: 2250 | E27: 0.59
A28: Break Lease | B28: 3770.55 | C28: 0.99 | D28: 3770.55 | E28: 0.99
A29: Late Fee | B29: 4154.73 | C29: 1.09 | D29: 4154.73 | E29: 1.09
A30: Utility Reimbursement Fee | B30: 11881.92 | C30: 3.11 | D30: 11881.92 | E30: 3.11
A31: Garbage Fee | B31: -3823.65 | C31: -1 | D31: -3823.65 | E31: -1
A32: Total FEES | B32: 23376.52 | C32: 6.12 | D32: 23376.52 | E32: 6.12
... A37: Total Operating Income | B37: 382240.25 | C37: 100 | D37: 382240.25 | E37: 100
A38: Expense
A39: CLEANING AND MAINTENANCE
A40: Supplies - Cleaning and Maitenance | B40: 244.91 | C40: 0.06 | D40: 244.91 | E40: 0.06
A41: Cleaning and Maintenance -Other | B41: 4439.29 | C41: 1.16 | D41: 4439.29 | E41: 1.16
A42: Total CLEANING AND MAINTENANCE | B42: 4684.2 | C42: 1.23 | D42: 4684.2 | E42: 1.23
A43: Permits & Licenses | B43: 680.35 | C43: 0.18 | D43: 680.35 | E43: 0.18
A44: CONTRACT SERVICES
A45: Elevator | B45: 270 | C45: 0.07 | D45: 270 | E45: 0.07
A46: Pool | B46: 1475.76 | C46: 0.39 | D46: 1475.76 | E46: 0.39
A47: Pest Control | B47: 21.21 | C47: 0.01 | D47: 21.21 | E47: 0.01
A48: Landscaping | B48: 4353 | C48: 1.14 | D48: 4353 | E48: 1.14
A49: Total CONTRACT SERVICES | B49: 6119.97 | C49: 1.6 | D49: 6119.97 | E49: 1.6
A50: LEGAL AND OTHER PROFESSIONAL FEES
A51: Legal | B51: 756.48 | C51: 0.2 | D51: 756.48 | E51: 0.2
A52: Total LEGAL AND OTHER PROFESSIONAL FEES | B52: 756.48 | C52: 0.2 | D52: 756.48 | E52: 0.2
A53: MANAGEMENT FEES
A54: Commissions/Placement Fee's
A55: Realtor Commissions | B55: 3147.5 | C55: 0.82 | D55: 3147.5 | E55: 0.82
A56: Total Commissions/Placement Fee's | B56: 3147.5 | C56: 0.82 | D56: 3147.5 | E56: 0.82
A57: Management fees | B57: 17546.05 | C57: 4.59 | D57: 17546.05 | E57: 4.59
A58: Total MANAGEMENT FEES | B58: 20693.55 | C58: 5.41 | D58: 20693.55 | E58: 5.41
A59: REPAIRS
A60: Plumbing | B60: 1500 | C60: 0.39 | D60: 1500 | E60: 0.39
A61: HVAC (Heat, Ventilation, Air) | B61: 2691.96 | C61: 0.7 | D61: 2691.96 | E61: 0.7
A62: General Maintenance Labor | B62: 8135.11 | C62: 2.13 | D62: 8135.11 | E62: 2.13
A63: Key/Lock Replacement | B63: 376 | C63: 0.1 | D63: 376 | E63: 0.1
A64: Supplies - R&M | B64: 24201.54 | C64: 6.33 | D64: 24201.54 | E64: 6.33
A65: Supplies - HVAC | B65: 341.33 | C65: 0.09 | D65: 341.33 | E65: 0.09
A66: Total REPAIRS | B66: 37245.94 | C66: 9.74 | D66: 37245.94 | E66: 9.74
A67: UTILITIES
A68: Electricity | B68: 4070 | C68: 1.06 | D68: 4070 | E68: 1.06
A69: Water & Sewer | B69: 16128.26 | C69: 4.22 | D69: 16128.26 | E69: 4.22
A70: Garbage and Recycling | B70: 9007.33 | C70: 2.36 | D70: 9007.33 | E70: 2.36
A71: Total UTILITIES | B71: 29205.59 | C71: 7.64 | D71: 29205.59 | E71: 7.64
A72: GENERAL & ADMINISTRATIVE
A73: Appfolio/Software Charges | B73: 792 | C73: 0.21 | D73: 792 | E73: 0.21
A74: Postage & Delivery | B74: 244.71 | C74: 0.06 | D74: 244.71 | E74: 0.06
A75: Misc. Expense/Other Gen & Admin Charges | B75: 750 | C75: 0.2 | D75: 750 | E75: 0.2
A76: Tenant Security Deposit Insurance | B76: 2438.59 | C76: 0.64 | D76: 2438.59 | E76: 0.64
A77: Total GENERAL & ADMINISTRATIVE | B77: 4225.3 | C77: 1.11 | D77: 4225.3 | E77: 1.11
A78: Advertising | B78: 2617.5 | C78: 0.68 | D78: 2617.5 | E78: 0.68
A79: Total Operating Expense | B79: 106228.88 | C79: 27.79 | D79: 106228.88 | E79: 27.79
A81: NOI - Net Operating Income | B81: 276011.37 | C81: 72.21 | D81: 276011.37 | E81: 72.21
A83: Other Income & Expense
A84: Other Expense
A85: CAPITAL EXPENSES
A86: Appliances | B86: 1395 | C86: 0.36 | D86: 1395 | E86: 0.36
A87: Remodel-Gen. Maintenance Labor | B87: 40859.39 | C87: 10.69 | D87: 40859.39 | E87: 10.69
A88: Remodel - Supplies | B88: 17886.5 | C88: 4.68 | D88: 17886.5 | E88: 4.68
A89: Remodel-Exterior Renovations | B89: 26529.17 | C89: 6.94 | D89: 26529.17 | E89: 6.94
A90: Administrative | B90: 750 | C90: 0.2 | D90: 750 | E90: 0.2
A91: Total CAPITAL EXPENSES | B91: 87420.06 | C91: 22.87 | D91: 87420.06 | E91: 22.87
A92: Total Other Expense | B92: 87420.06 | C92: 22.87 | D92: 87420.06 | E92: 22.87
A94: Net Other Income | B94: -87420.06 | C94: -22.87 | D94: -87420.06 | E94: -22.87
A96: Total Income | B96: 382240.25 | C96: 100 | D96: 382240.25 | E96: 100
A97: Total Expense | B97: 193648.94 | C97: 50.66 | D97: 193648.94 | E97: 50.66
A99: Net Income | B99: 188591.31 | C99: 49.34 | D99: 188591.31 | E99: 49.34
A101: Change in Assets & Liabilities
A102: Accounts Receivable | B102: -40558.03 | D102: -44358.03
A103: Mgmt Held Security Deposits | B103: 2590.01 | D103: 85275.01
A104: Prepaid Rent | B104: 11913.82 | D104: 11913.82
A105: Accounts Payable | B105: 27391.95 | D105: 27391.95
A106: Net Change in Assets & Liabilities | B106: 1337.75 | D106: 80222.75
A108: Other Items
A109: SECURITY DEPOSITS | B109: 2590.01 | D109: 85275.01
A110: Owner Contribution | B110: 52942.95 | D110: 52942.95
A111: Owner Distribution | B111: -232527 | D111: -232527
A112: Net Other Items | B112: -176994.04 | D112: -94309.04
A114: Cash Flow | B114: 12935.02 | D114: 174505.02
...
